[
  {
    "id": 9323,
    "mediaId": 2790,
    "date": "2022-03-24",
    "sentence": "\"This bill to me is all about biology,\" said Republican Rep. <span class='selected-term'>Shawnna Bolick</span>, who said she played on a coed team in the 1980s but could not have made the high school boys team.",
    "author": "The Associated Press",
    "title": "Arizona Legislature passes 2 bills to curb transgender rights"
  },
  {
    "id": 9402,
    "mediaId": 2640,
    "date": "2022-03-24",
    "sentence": "\"This bill to me is all about biology,\" said Republican Rep. <span class='selected-term'>Shawnna Bolick</span>.",
    "author": "",
    "title": "Lawmakers Vote to Prohibit Minors' Transgender Surgery"
  },
  {
    "id": 9702,
    "mediaId": 2607,
    "date": "2022-03-24",
    "sentence": "“This bill to me is all about biology,” said Republican Rep. <span class='selected-term'>Shawnna Bolick</span>, who said she played on a coed team in the 1980s but could not have made the high school boys team.",
    "author": "Jonathan J. Cooper",
    "title": "Arizona lawmakers vote to restrict trans athletes, surgeries"
  }
]