[
  {
    "id": 15710,
    "mediaId": 8422,
    "date": "2022-03-14",
    "sentence": "",
    "author": "Tribune News Service",
    "title": "Column: What approach will new Chicago Bears GM Ryan Poles take into free agency?"
  },
  {
    "id": 11326,
    "mediaId": 6435,
    "date": "2022-03-14",
    "sentence": "",
    "author": "Brad Biggs",
    "title": "Column: What approach will new Chicago Bears GM Ryan Poles take into free agency?"
  },
  {
    "id": 11277,
    "mediaId": 2677,
    "date": "2022-03-14",
    "sentence": "One source said the Bears could be in play for Los Angeles Rams center <span class='selected-term'>Brian Allen</span>, a Hinsdale Central graduate who played at Michigan State.",
    "author": "Tribune News Service",
    "title": "Column: What approach will new Chicago Bears GM Ryan Poles take into free agency?"
  },
  {
    "id": 11560,
    "mediaId": 2525,
    "date": "2022-03-18",
    "sentence": "They were in the running to sign Los Angeles Rams center <span class='selected-term'>Brian Allen</span> but couldn’t finalize a deal.",
    "author": "Tribune News Service",
    "title": "Column: Ryan Poles’ calculated start to free agency shows the long timeline of the Chicago Bears rebuild"
  }
]