[
  {
    "id": 1789,
    "mediaId": 151,
    "date": "5/3/2022 12:00:00 AM",
    "sentence": "",
    "author": "",
    "title": "POLITICO Playbook: Breaking down Alito's Roe bombshell"
  },
  {
    "id": 1789,
    "mediaId": 151,
    "date": "5/3/2022 12:00:00 AM",
    "sentence": "",
    "author": "",
    "title": "POLITICO Playbook: Breaking down Alito's Roe bombshell"
  },
  {
    "id": 3185,
    "mediaId": 65,
    "date": "5/9/2022 12:00:00 AM",
    "sentence": "Claimed the 2018 Georgia gubernatorial election was stolen' from Stacey Abrams\nStacey Abrams acknowledged she didn't win but never officially conceded her Georgia gubernatorial defeat against her GOP rival <span class='selected-term'>Brian Kemp</span> in 2018, drawing criticism from conservatives that she was questioning the integrity of her own election.",
    "author": "",
    "title": "Karine Jean-Pierre: 10 things to know about the new White House press secretary"
  }
]