[
  {
    "id": 1401,
    "mediaId": 43,
    "date": "2/10/2022 12:00:00 AM",
    "sentence": "",
    "author": "",
    "title": "Morning Digest: Daily Kos Elections is launching"
  },
  {
    "id": 1961,
    "mediaId": 43,
    "date": "4/25/2022 12:00:00 AM",
    "sentence": "x\nIn #GaGovDebate, <span class='selected-term'>Brian Kemp</span> and David Perdue showed they are bad for each other  and worse for Georgia.",
    "author": "",
    "title": "If elections are about the future, Georgia's gubernatorial race suggests Republicans are screwed"
  }
]