{
  "id": 13831,
  "mediaId": 8390,
  "date": "2022-03-21",
  "headline": "Vance won't speak at Minnesota GOP event after criticism over Ukraine remarks",
  "image": "https://dehayf5mhw1h7.cloudfront.net/wp-content/uploads/sites/489/2022/03/21154513/vancejd.jpg",
  "link": "https://www.onnradio.com/2022/03/21/vance-wont-speak-at-minnesota-gop-event-after-criticism-over-ukraine-remarks/",
  "mediaOutlet": "Ohio News Network",
  "biasRatingId": 1,
  "wordCount": 0,
  "author": "",
  "authorUrl": "",
  "termIds": [
    0
  ],
  "sentences": [
    "Vance will not speak at a Republican Party of Minnesota event scheduled for next month, with Matt Schlapp, chairman of the American Conservative Union, taking his place.A state party official told the Minneapolis Star…",
    "Ohio Senate candidate J.D."
  ]
}