[
  {
    "id": 2418,
    "mediaId": 129,
    "date": "1/11/2022 12:00:00 AM",
    "sentence": "Mandela Barnes and State Treasurer Sarah Godlewski, along with <span class='selected-term'>Alex Lasry</span>, an executive with the Milwaukee Bucks, and Tom Nelson, a county executive.",
    "author": "",
    "title": "Nobody's Getting Special Treatment in 2022"
  },
  {
    "id": 2418,
    "mediaId": 129,
    "date": "1/11/2022 12:00:00 AM",
    "sentence": "Mandela Barnes and State Treasurer Sarah Godlewski, along with <span class='selected-term'>Alex Lasry</span>, an executive with the Milwaukee Bucks, and Tom Nelson, a county executive.",
    "author": "",
    "title": "Nobody's Getting Special Treatment in 2022"
  }
]