[
  {
    "id": 3670,
    "mediaId": 157,
    "date": "2022-00-12",
    "sentence": "",
    "author": "Sarah K. Burris",
    "title": "Florida principal threatened to cut off gay class president's graduation speech if he mentioned LGBT issues",
    "sentiment": "0"
  },
  {
    "id": 3670,
    "mediaId": 157,
    "date": "2022-00-12",
    "sentence": "",
    "author": "Sarah K. Burris",
    "title": "Florida principal threatened to cut off gay class president's graduation speech if he mentioned LGBT issues",
    "sentiment": "0.0"
  }
]