[
  {
    "id": 3787,
    "mediaId": 558,
    "date": "5/10/2022 12:00:00 AM",
    "sentence": "",
    "author": "",
    "title": "Florida school yearbook on hold over student protest photos",
    "sentiment": "0"
  },
  {
    "id": 3791,
    "mediaId": 558,
    "date": "5/10/2022 12:00:00 AM",
    "sentence": "",
    "author": "",
    "title": "Florida school yearbook on hold over student protest photos",
    "sentiment": "0"
  },
  {
    "id": 3798,
    "mediaId": 25,
    "date": "5/10/2022 12:00:00 AM",
    "sentence": "",
    "author": "",
    "title": "Florida school yearbook on hold after students protest \"Don't Say Gay\" bill in photos",
    "sentiment": "0"
  }
]