[
  {
    "id": 7033,
    "mediaId": 675,
    "date": "2/13/2022 12:00:00 AM",
    "sentence": "",
    "author": "WND News Services",
    "title": "The mystery of the migrant kids"
  },
  {
    "id": 5261,
    "mediaId": 593,
    "date": "4/7/2022 12:00:00 AM",
    "sentence": "OTHER RESTRICTIONS\nFLORIDA: Republican Governor <span class='selected-term'>Ron DeSantis</span> signed a bill that bans any classroom conversation, including instruction on sexual orientation and gender identity for children in kindergarten through third grade, and says all teaching for grades 4-12 must be \"age-appropriate,\" wording that is not defined in the bill.",
    "author": "Maria Caspani",
    "title": "Factbox-The Onslaught Of U.S. Laws Targeting Transgender Youth"
  },
  {
    "id": 6971,
    "mediaId": 151,
    "date": "4/11/2022 12:00:00 AM",
    "sentence": "",
    "author": "",
    "title": "Crypto's campaign year"
  },
  {
    "id": 6300,
    "mediaId": 43,
    "date": "4/19/2022 12:00:00 AM",
    "sentence": "The New Yorker: Satire from the Borowitz Report: DeSantis Warns That Math Makes Children Gay\nTALLAHASSEE (The Borowitz Report)Proposing a sweeping ban on math in Floridas classrooms, Governor <span class='selected-term'>Ron DeSantis</span> asserted that the latest research? indicates that math makes children gay.?\nFor years, liberals in the education mafia have brainwashed Americans into thinking that our children should learn to add, subtract, multiply, and divide,? he told reporters.",
    "author": "",
    "title": "for Bluesday, April 19th"
  },
  {
    "id": 5066,
    "mediaId": 19,
    "date": "4/20/2022 12:00:00 AM",
    "sentence": "The pact is signed by the following governors:\nGovernors Doug Ducey (AZ), Greg Abbott (TX), Kay Ivey (AL), Mike Dunleavy (AK), Asa Hutchinson (AR), <span class='selected-term'>Ron DeSantis</span> (FL), Brian Kemp (GA), Brad Little (ID), Eric Holcomb (IN), Kim Reynolds (IA), Larry Hogan (MD), Tate Reeves (MS), Mike Parson (MO), Greg Gianforte (MT), Pete Ricketts (NE), Chris Sununu (NH), Doug Burgum (ND), Mike DeWine (OH), Kevin Stitt (OK), Henry McMaster (SC), Kristi Noem (SD), Bill Lee (TN), Spencer Cox (UT), Glenn Youngkin (VA), Jim Justice (WV), and Mark Gordon (WY).",
    "author": "Bob Price",
    "title": "26 Governors Mobilize Against Migration Chaos at Border"
  },
  {
    "id": 6163,
    "mediaId": 157,
    "date": "4/25/2022 12:00:00 AM",
    "sentence": "At a NewsMax townhall last week, he used Florida Governor <span class='selected-term'>Ron DeSantis</span> bid to strip Disney of a special taxing district in retaliation for opposing the states dont say gay? legislation as an example of a politician who knows what time it is.?\nJ.D.",
    "author": "Nick Evans",
    "title": "'We love Trump, but he's not God': Trump fans unmoved by his endorsement of J.D. Vance"
  },
  {
    "id": 4873,
    "mediaId": 238,
    "date": "4/28/2022 12:00:00 AM",
    "sentence": "",
    "author": "",
    "title": "Opinion The new Republican statism"
  },
  {
    "id": 4368,
    "mediaId": 238,
    "date": "4/29/2022 12:00:00 AM",
    "sentence": "",
    "author": "",
    "title": "Florida reintroduces math textbooks scrubbed of woke content"
  },
  {
    "id": 4372,
    "mediaId": 63,
    "date": "4/29/2022 12:00:00 AM",
    "sentence": "",
    "author": "Alison Durkee",
    "title": "Most AmericansEven RepublicansOppose Florida GOPs Attacks On Disney, Poll Suggests"
  },
  {
    "id": 4377,
    "mediaId": 195,
    "date": "4/29/2022 12:00:00 AM",
    "sentence": "",
    "author": "Armstrong Williams",
    "title": "Someone like Trump  but not Trump"
  },
  {
    "id": 4393,
    "mediaId": 65,
    "date": "4/29/2022 12:00:00 AM",
    "sentence": "",
    "author": "Lynne Jordal Martin",
    "title": "What Joe knew about Hunter, say 'no' to college and more Fox News Opinion"
  },
  {
    "id": 4397,
    "mediaId": 124,
    "date": "4/29/2022 12:00:00 AM",
    "sentence": "",
    "author": "",
    "title": "Most Americans don't support politicians punishing firms for their views, Reuters/Ipsos poll finds"
  },
  {
    "id": 4408,
    "mediaId": 151,
    "date": "4/29/2022 12:00:00 AM",
    "sentence": "",
    "author": "",
    "title": "The fall of the White House correspondent"
  },
  {
    "id": 4432,
    "mediaId": 124,
    "date": "4/29/2022 12:00:00 AM",
    "sentence": "",
    "author": "",
    "title": "Elon Musks uneasy relationship with the left explodes over Twitter takeover"
  },
  {
    "id": 4437,
    "mediaId": 98,
    "date": "4/29/2022 12:00:00 AM",
    "sentence": "",
    "author": "David Lauter",
    "title": "Is politics making people sick? A lot of young people say so"
  },
  {
    "id": 4439,
    "mediaId": 558,
    "date": "4/29/2022 12:00:00 AM",
    "sentence": "Governor <span class='selected-term'>Ron DeSantis</span> deserves the medal of honor for standing up to these woke bullies who have pushed their subversive materials on an unsuspecting public.",
    "author": "Roger Guffey",
    "title": "Clearly, Florida on point about math textbooks being woke indoctrination manuals"
  },
  {
    "id": 4440,
    "mediaId": 593,
    "date": "4/29/2022 12:00:00 AM",
    "sentence": "A bipartisan majority of U.S. voters oppose politicians punishing companies over their stances on social issues, a cold reception for campaigns like Florida Governor <span class='selected-term'>Ron DeSantis</span>' against Walt Disney Co, a Reuters/Ipsos poll found.",
    "author": "Jason Lange",
    "title": "Americans Do Not Support Politicians Punishing Firms For Their Views -Reuters/Ipsos"
  },
  {
    "id": 4444,
    "mediaId": 65,
    "date": "4/29/2022 12:00:00 AM",
    "sentence": "",
    "author": "Fox News Staff",
    "title": "Ingraham: DeSantis has embraced policies that once seemed unthinkable"
  },
  {
    "id": 4445,
    "mediaId": 558,
    "date": "4/29/2022 12:00:00 AM",
    "sentence": "By Jason Lange\nWASHINGTON (Reuters) - A bipartisan majority of U.S. voters oppose politicians punishing companies over their stances on social issues, a cold reception for campaigns like Florida Governor <span class='selected-term'>Ron DeSantis</span>' against Walt Disney Co, a Reuters/Ipsos poll found.",
    "author": "Jason Lange",
    "title": "Americans do not support politicians punishing firms for their views -Reuters/Ipsos"
  },
  {
    "id": 4337,
    "mediaId": 261,
    "date": "4/30/2022 12:00:00 AM",
    "sentence": "Imagine all of America subjected to the casual cruelty and hypocrisy of a <span class='selected-term'>Ron DeSantis</span> or a Greg Abbott.",
    "author": "Jill Lawrence",
    "title": "Democrats must play hardball to survive 2022 midterms | Opinion"
  },
  {
    "id": 4280,
    "mediaId": 558,
    "date": "5/1/2022 12:00:00 AM",
    "sentence": "Heilemann and Sorkin discuss how Walt Disney Company found itself at the center of Americas culture wars, what Florida governor <span class='selected-term'>Ron DeSantis</span> seeks to gain from punishing Disney over its opposition to the states so-called Dont Say Gay? law, and the increasingly strained relationship between Republicans and corporate America.",
    "author": "",
    "title": "Gov. Ron DeSantis May Lose to Disney  But Win With Voters"
  },
  {
    "id": 4292,
    "mediaId": 163,
    "date": "5/1/2022 12:00:00 AM",
    "sentence": "Other potential Republican contenders in 2024 include Florida Governor <span class='selected-term'>Ron DeSantis</span>, former Vice President Mike Pence and former Secretary of State Mike Pompeo.",
    "author": "Doina Chiacu",
    "title": "Republican Hutchinson, at odds with Trump, eyes 2024 U.S. presidential run"
  },
  {
    "id": 4298,
    "mediaId": 593,
    "date": "5/1/2022 12:00:00 AM",
    "sentence": "Other potential Republican contenders in 2024 include Florida Governor <span class='selected-term'>Ron DeSantis</span>, former Vice President Mike Pence and former Secretary of State Mike Pompeo.",
    "author": "Doina Chiacu",
    "title": "Republican Hutchinson, At Odds With Trump, Eyes 2024 U.S. Presidential Run"
  },
  {
    "id": 4303,
    "mediaId": 132,
    "date": "5/1/2022 12:00:00 AM",
    "sentence": "",
    "author": "Sol Wachtler",
    "title": "What critical race theory is  and what it is not"
  },
  {
    "id": 4304,
    "mediaId": 302,
    "date": "5/1/2022 12:00:00 AM",
    "sentence": "My concern: If Gov <span class='selected-term'>Ron DeSantis</span> were to lose, would he accept that result or would his newly formed election fraud division cry foul and claim the election was stolen?",
    "author": "",
    "title": "Learn from our history  the heroic and the uncomfortable | Letters"
  },
  {
    "id": 4307,
    "mediaId": 391,
    "date": "5/1/2022 12:00:00 AM",
    "sentence": "",
    "author": "",
    "title": "Ukrainian president is a true leader; mass shootings need attention | READER COMMENTARY"
  },
  {
    "id": 4309,
    "mediaId": 151,
    "date": "5/1/2022 12:00:00 AM",
    "sentence": "Thats why <span class='selected-term'>Ron DeSantis</span> is one step ahead  first you ban the math textbooks, then nobody knows how to count the votes.",
    "author": "",
    "title": "Trevor Noah's best jokes at the WHCD"
  },
  {
    "id": 4183,
    "mediaId": 593,
    "date": "5/2/2022 12:00:00 AM",
    "sentence": "FLORIDA: Republican Governor <span class='selected-term'>Ron DeSantis</span> in April signed a 15-week abortion ban, which allows exceptions for medical emergencies or if the fetus has a fatal abnormality.",
    "author": "Gabriella Borter",
    "title": "Factbox-Restrictions Vs Protections: How U.S. States Are Taking Sides On Abortion"
  },
  {
    "id": 4185,
    "mediaId": 63,
    "date": "5/2/2022 12:00:00 AM",
    "sentence": "I know Elon is just deeply committed to the idea of freedom of expression.?\nFree speech doesnt necessarily mean good ideas, to be clear,? he added, but to have a robust debate around ideas is how we actually come to reasonable conclusions.?\nDeSantis vs. Disney\nThe top GOP donor this election cycle, with some $40 million in political contributions, Griffin has also been a big backer of Florida governor <span class='selected-term'>Ron DeSantis</span>.",
    "author": "Chase Peterson-Withorn",
    "title": "Billionaire GOP Megadonor Ken Griffin: I Dont Appreciate Governor DeSantis Going After Disneys Tax Status."
  },
  {
    "id": 4187,
    "mediaId": 558,
    "date": "5/2/2022 12:00:00 AM",
    "sentence": "FLORIDA: Republican Governor <span class='selected-term'>Ron DeSantis</span> in April signed a 15-week abortion ban, which allows exceptions for medical emergencies or if the fetus has a fatal abnormality.",
    "author": "Gabriella Borter",
    "title": "Factbox-Restrictions vs protections: How U.S. states are taking sides on abortion"
  },
  {
    "id": 4188,
    "mediaId": 558,
    "date": "5/2/2022 12:00:00 AM",
    "sentence": "FLORIDA: Republican Governor <span class='selected-term'>Ron DeSantis</span> in April signed a 15-week abortion ban, which allows exceptions for medical emergencies or if the fetus has a fatal abnormality.",
    "author": "Gabriella Borter",
    "title": "Factbox-Restrictions vs protections: How U.S. states are taking sides on abortion"
  },
  {
    "id": 4192,
    "mediaId": 120,
    "date": "5/2/2022 12:00:00 AM",
    "sentence": "",
    "author": "Ja'han Jones",
    "title": "The GOPs political stunts come at a high cost for Americans"
  },
  {
    "id": 4194,
    "mediaId": 65,
    "date": "5/2/2022 12:00:00 AM",
    "sentence": "",
    "author": "Kelly Laco",
    "title": "DeSantis accuses Disney of cozying up to CCP, making 'a fortune' without mentioning atrocities"
  },
  {
    "id": 4205,
    "mediaId": 237,
    "date": "5/2/2022 12:00:00 AM",
    "sentence": "Thats why <span class='selected-term'>Ron DeSantis</span> is one step ahead  first you ban the math textbooks, then nobody knows how to count the votes.",
    "author": "Asher Notheis",
    "title": "DeSantis blasts Trevor Noah's 'lie' he attended Correspondents' Dinner"
  },
  {
    "id": 4208,
    "mediaId": 943,
    "date": "5/2/2022 12:00:00 AM",
    "sentence": "",
    "author": "",
    "title": "Letters: The Obama Presidential Center will be a boon to Jackson Park area"
  },
  {
    "id": 4223,
    "mediaId": 558,
    "date": "5/2/2022 12:00:00 AM",
    "sentence": "",
    "author": "Jimena Tavel",
    "title": "Who is Daniel Foganholi, the new Broward School Board member appointed by DeSantis?"
  },
  {
    "id": 4243,
    "mediaId": 18,
    "date": "5/2/2022 12:00:00 AM",
    "sentence": "",
    "author": "Editorial",
    "title": "Editorial: Disney, DeSantis must compromise"
  },
  {
    "id": 4248,
    "mediaId": 223,
    "date": "5/2/2022 12:00:00 AM",
    "sentence": "Or do you have faith in the proven leadership of Donald Trump, Florida Governor <span class='selected-term'>Ron DeSantis</span>, Virginia Governor Glenn Youngkin and dozens of other Republicans who stand ready to swing the pendulum of America back to sanity in 2022.",
    "author": "Tom Tradup",
    "title": "Democrats Gleefully Bankrupting America"
  },
  {
    "id": 4261,
    "mediaId": 19,
    "date": "5/2/2022 12:00:00 AM",
    "sentence": "You see, what I like about <span class='selected-term'>Ron DeSantis</span> is if Trump was the original Terminator, DeSantis is the T-1000.",
    "author": "Joel B. Pollak",
    "title": "Ron DeSantis: Trevor Noah Lying About My Presence at White House Correspondents Dinner"
  },
  {
    "id": 4269,
    "mediaId": 195,
    "date": "5/2/2022 12:00:00 AM",
    "sentence": "",
    "author": "",
    "title": "Rising: May 2, 2022"
  },
  {
    "id": 4276,
    "mediaId": 157,
    "date": "5/2/2022 12:00:00 AM",
    "sentence": "Theyre purging the party of old-line fiscal conservatives? like Liz Cheney; and the savagely bigoted and anti-gay <span class='selected-term'>Ron DeSantis</span> is their new savior.",
    "author": "Thom Hartmann",
    "title": "A third of America is lost to hate: Is it time to move on?"
  },
  {
    "id": 4100,
    "mediaId": 136,
    "date": "5/3/2022 12:00:00 AM",
    "sentence": "Florida Governor <span class='selected-term'>Ron DeSantis</span> believes that the United States is out-of-step on abortion when compared to other industrialized nations, including those in Europe, and said the U.S. is \"more in line\" with China and North Korea regarding abortion policy.",
    "author": "Adam Staten",
    "title": "Ron DeSantis Likens U.S. Abortion Laws to North Korea, China"
  },
  {
    "id": 4115,
    "mediaId": 558,
    "date": "5/3/2022 12:00:00 AM",
    "sentence": "Mayor Francis Suarez and Florida State Governor <span class='selected-term'>Ron DeSantis</span> are crypto advocates.",
    "author": "Bob Mason",
    "title": "Crypto-Backed Mortgages on the Rise Despite Crypto Market Pullback"
  },
  {
    "id": 4117,
    "mediaId": 65,
    "date": "5/3/2022 12:00:00 AM",
    "sentence": "",
    "author": "",
    "title": "Hillary Clinton mocked for maskless Met Gala photos while being doted on by masked staff"
  },
  {
    "id": 4119,
    "mediaId": 1067,
    "date": "5/3/2022 12:00:00 AM",
    "sentence": "",
    "author": "Skyler Swisher",
    "title": "Top DeSantis megadonor doesnt appreciate him targeting Disney"
  },
  {
    "id": 4120,
    "mediaId": 195,
    "date": "5/3/2022 12:00:00 AM",
    "sentence": "",
    "author": "Kimberly Wehle",
    "title": "SCOTUS leaked abortion opinion is rooted in a time women had no rights"
  },
  {
    "id": 4121,
    "mediaId": 169,
    "date": "5/3/2022 12:00:00 AM",
    "sentence": "",
    "author": "Jon Skolnik",
    "title": "Megyn Kelly pushes back after Bill Barr suggest SCOTUS leaker could be criminally prosecuted"
  },
  {
    "id": 4132,
    "mediaId": 98,
    "date": "5/3/2022 12:00:00 AM",
    "sentence": "When outrage by employees and others finally prompted the company to take a stand, its reversal only made it a convenient target for Floridas brutish Republican governor, <span class='selected-term'>Ron DeSantis</span>.",
    "author": "Michael Hiltzik",
    "title": "Column: Corporations left California for lower taxes and fewer regulations. Will abortion rights bring them back?"
  },
  {
    "id": 4144,
    "mediaId": 129,
    "date": "5/3/2022 12:00:00 AM",
    "sentence": "Tension between businesses and politicians may intensify\nDisneys recent battles with <span class='selected-term'>Ron DeSantis</span>, Floridas Republican governor, over a law prohibiting discussion of gender identity in some public schools cost the company its special tax privileges and good will from key Republicans.",
    "author": "",
    "title": "U.S. job openings hit a high point, 11.5 million, in March."
  },
  {
    "id": 4150,
    "mediaId": 558,
    "date": "5/3/2022 12:00:00 AM",
    "sentence": "Florida Republican Governor <span class='selected-term'>Ron DeSantis</span> signed into law the Stop the Wrongs to Our Kids and Employees Act or Stop WOKE Act a bill that regulates how schools and employers can talk about race and genderon April 22.\nWe believe an important component of freedom in the state of Florida is the freedom from having oppressive ideologies imposed upon you without your consent,? DeSantis said at the bill signing event at Mater Academy Charter Middle/High School in Hialeah Gardens last month.",
    "author": "Amiah Taylor",
    "title": "How Floridas Stop WOKE Act could impose a chilling effect on diversity efforts in the workplace"
  },
  {
    "id": 4152,
    "mediaId": 163,
    "date": "5/3/2022 12:00:00 AM",
    "sentence": "FLORIDA: Republican Governor <span class='selected-term'>Ron DeSantis</span> in April signed a 15-week abortion ban, which allows exceptions for medical emergencies or if the fetus has a fatal abnormality.",
    "author": "Gabriella Borter",
    "title": "Factbox: Restrictions vs protections: How U.S. states are taking sides on abortion"
  },
  {
    "id": 4168,
    "mediaId": 129,
    "date": "5/3/2022 12:00:00 AM",
    "sentence": "",
    "author": "",
    "title": "Get Ready for Another Energy Price Spike: High Electric Bills"
  },
  {
    "id": 4049,
    "mediaId": 675,
    "date": "5/4/2022 12:00:00 AM",
    "sentence": "",
    "author": "Art Moore",
    "title": "Disney's stock plummets amid embrace of woke politics"
  },
  {
    "id": 4051,
    "mediaId": 302,
    "date": "5/4/2022 12:00:00 AM",
    "sentence": "",
    "author": "Ian Hodgson",
    "title": "What you need to know about the future of abortion in Florida"
  },
  {
    "id": 4058,
    "mediaId": 132,
    "date": "5/4/2022 12:00:00 AM",
    "sentence": "In March, Floridas Republican governor, <span class='selected-term'>Ron DeSantis</span>, signed the Parental Rights in Education Bill,? which reinforces parents rights to make decisions regarding the upbringing of their children.? The bill prohibits classroom instruction on sexual orientation or gender identity in kindergarten through third grade and prohibits instruction that is not age appropriate for students and requires school districts to adopt procedures for notifying parents if there is a change in services from the school regarding a childs mental, emotional or physical health or well-being.",
    "author": "Lynn Schmidt",
    "title": "Give peace a chance in America's culture wars"
  },
  {
    "id": 4060,
    "mediaId": 129,
    "date": "5/4/2022 12:00:00 AM",
    "sentence": "",
    "author": "",
    "title": "Live Updates: Supreme Court Weighs Future Role and Final Word on Abortion"
  },
  {
    "id": 4065,
    "mediaId": 129,
    "date": "5/4/2022 12:00:00 AM",
    "sentence": "",
    "author": "",
    "title": "Uber continues its recovery from the pandemic lull but loses $5.6 billion from investments."
  },
  {
    "id": 4067,
    "mediaId": 136,
    "date": "5/4/2022 12:00:00 AM",
    "sentence": "In Florida, there is also continuing outcry over HB 1557, the legislation backed by Governor <span class='selected-term'>Ron DeSantis</span> which critics have dubbed the \"Don't Say Gay\" bill.",
    "author": "Ewan Palmer",
    "title": "'It's A Cult': Mike Huckabee Accused of Indoctrinating Kids With Trump Book"
  },
  {
    "id": 4079,
    "mediaId": 124,
    "date": "5/4/2022 12:00:00 AM",
    "sentence": "",
    "author": "",
    "title": "Yelp and Meta's Sandberg respond to draft opinion that would strike down Roe v. Wade"
  },
  {
    "id": 4087,
    "mediaId": 129,
    "date": "5/4/2022 12:00:00 AM",
    "sentence": "",
    "author": "",
    "title": "Abortion Is a Business Issue"
  },
  {
    "id": 4094,
    "mediaId": 43,
    "date": "5/4/2022 12:00:00 AM",
    "sentence": "Amazon and other companies have been eager to distance themselves from the end of Roe, since they haven't forked over cash to make <span class='selected-term'>Ron DeSantis</span> president yet and so Ron hasn't been able to pass new nationwide laws punishing them for doing so.",
    "author": "Hunter\nDaily Kos Staff",
    "title": "These are some of the companies that funded the end of Roe v. Wade"
  },
  {
    "id": 3978,
    "mediaId": 65,
    "date": "5/5/2022 12:00:00 AM",
    "sentence": "\"This is disgustingly insensitive,\" tweeted <span class='selected-term'>Ron DeSantis</span> spokesperson Christina Pushaw.",
    "author": "",
    "title": "Conservatives roast comedy writer for saying nobody mourns 'miscarriages': Delete your account"
  },
  {
    "id": 3984,
    "mediaId": 323,
    "date": "5/5/2022 12:00:00 AM",
    "sentence": "",
    "author": "Elliott Abrams and Eric Cohen",
    "title": "Ron DeSantis Is Persona Non Grata at a Holocaust Memorial"
  },
  {
    "id": 4005,
    "mediaId": 223,
    "date": "5/5/2022 12:00:00 AM",
    "sentence": "",
    "author": "Larry Elder",
    "title": "The Conservative Surge in Twitter Followers -- The Elon Musk Effect?"
  },
  {
    "id": 4006,
    "mediaId": 19,
    "date": "5/5/2022 12:00:00 AM",
    "sentence": "",
    "author": "Hannah Bleau",
    "title": "Ron DeSantis on the National Day of Prayer: Prayer Makes a Difference"
  },
  {
    "id": 4010,
    "mediaId": 187,
    "date": "5/5/2022 12:00:00 AM",
    "sentence": "Recent polls have found majority opposition in Texas to a ban passed there, and in Florida to the law Governor <span class='selected-term'>Ron DeSantis</span> recently signed prohibiting abortions after 15 weeks gestation.",
    "author": "Ronald Brownstein",
    "title": "Americas Blue-Red Divide Is About to Get Starker"
  },
  {
    "id": 4013,
    "mediaId": 157,
    "date": "5/5/2022 12:00:00 AM",
    "sentence": "",
    "author": "Matthew Chapman",
    "title": "Ron DeSantis banned from NY Museum of Jewish Heritage ahead of speaking role at the facility: report"
  },
  {
    "id": 4024,
    "mediaId": 19,
    "date": "5/5/2022 12:00:00 AM",
    "sentence": "",
    "author": "John Nolte",
    "title": "Nolte: Rematch Poll Shows Trump Defeating Biden by 14 Points"
  },
  {
    "id": 3897,
    "mediaId": 558,
    "date": "5/6/2022 12:00:00 AM",
    "sentence": "Florida Governor <span class='selected-term'>Ron DeSantis</span> signed a bill in April stripping Disney of self-governing authority at its Orlando-area parks in retaliation for its opposition to a new state law that limits the teaching of LGBTQ issues in schools.",
    "author": "",
    "title": "'Like family': Japan's virtual YouTubers make millions from fans"
  },
  {
    "id": 3907,
    "mediaId": 163,
    "date": "5/6/2022 12:00:00 AM",
    "sentence": "Governor <span class='selected-term'>Ron DeSantis</span>, who is running for re-election and is considered a top Republican contender for the 2024 presidential election, signed the bill into law last year after it passed the Republican-majority legislature.",
    "author": "Joseph Ax",
    "title": "U.S. appeals court reinstates Florida voting limits that judge had deemed discriminatory"
  },
  {
    "id": 3920,
    "mediaId": 441,
    "date": "5/6/2022 12:00:00 AM",
    "sentence": "Arizona Governor Doug Ducey, Florida Governor <span class='selected-term'>Ron DeSantis</span> and Oklahoma Governor Kevin Stitt, all Republicans, signed abortion bans with no exceptions this year.",
    "author": "Ryan Teague Beckwith",
    "title": "Poll Shows Risk for Republicans Backing No-Exception Abortion Bans"
  },
  {
    "id": 3923,
    "mediaId": 558,
    "date": "5/6/2022 12:00:00 AM",
    "sentence": "Video Transcript\nSEANA SMITH: Critical debates lately, especially Disney with Florida Governor <span class='selected-term'>Ron DeSantis</span>, but with the bombshell leak of a draft opinion from the Supreme Court, which will likely overturn Roe versus Wade, the C-suite has been mostly quiet.",
    "author": "",
    "title": "Roe v. Wade: How corporate America has responded to the Supreme Court draft opinion"
  },
  {
    "id": 3924,
    "mediaId": 593,
    "date": "5/6/2022 12:00:00 AM",
    "sentence": "Governor <span class='selected-term'>Ron DeSantis</span>, who is running for re-election and is considered a top Republican contender for the 2024 presidential election, signed the bill into law last year after it passed the Republican-majority legislature.",
    "author": "Joseph Ax",
    "title": "U.S. Appeals Court Reinstates Florida Voting Limits That Judge Had Deemed Discriminatory"
  },
  {
    "id": 3925,
    "mediaId": 593,
    "date": "5/6/2022 12:00:00 AM",
    "sentence": "Florida Governor <span class='selected-term'>Ron DeSantis</span>, a rising star in the Republican party, signed a bill in April stripping Disney of self-governing authority at its Orlando-area parks in retaliation for its opposition to a new state law that limits the teaching of LGBTQ issues in schools.",
    "author": "Doyinsola Oladipo and Arriana McLymore",
    "title": "Yelp, Other Companies Take Stance On Abortion Rights With Travel Benefit"
  },
  {
    "id": 3929,
    "mediaId": 558,
    "date": "5/6/2022 12:00:00 AM",
    "sentence": "",
    "author": "",
    "title": "Conservative urges American Christians to reject the new right's authoritarian impulses"
  },
  {
    "id": 3932,
    "mediaId": 558,
    "date": "5/6/2022 12:00:00 AM",
    "sentence": "Florida Governor <span class='selected-term'>Ron DeSantis</span>, a rising star in the Republican party, signed a bill in April stripping Disney of self-governing authority at its Orlando-area parks in retaliation for its opposition to a new state law that limits the teaching of LGBTQ issues in schools.",
    "author": "",
    "title": "Yelp, other companies take stance on abortion rights with travel benefit"
  },
  {
    "id": 3944,
    "mediaId": 223,
    "date": "5/6/2022 12:00:00 AM",
    "sentence": "View Cartoon\nMickey Mouse fell for the trap laid out by Governor <span class='selected-term'>Ron DeSantis</span> and Florida Republicans, as woke Disney had its special tax status removed after opposing popular legislation stopping the indoctrination of Americas children.",
    "author": "Townhall.com Staff",
    "title": "Leftist Abortion Cult Goes Nuclear"
  },
  {
    "id": 3966,
    "mediaId": 129,
    "date": "5/6/2022 12:00:00 AM",
    "sentence": "Right now, Republicans of all stripes  <span class='selected-term'>Ron DeSantis</span>, J.D.",
    "author": "",
    "title": "Donald Trump Didnt Hijack the G.O.P. He Understood It."
  },
  {
    "id": 3967,
    "mediaId": 43,
    "date": "5/6/2022 12:00:00 AM",
    "sentence": "[]\nRubio, who was a favorite of corporate donors during his 2016 presidential bid, has recently called corporations the instrument of anti-American ideologies,? a view echoed by Florida Governor <span class='selected-term'>Ron DeSantis</span>, another potential GOP presidential contender.",
    "author": "",
    "title": "Overnight News Digest: Barricades erected around Supreme Court; Mariupol defenders make their stand"
  },
  {
    "id": 3887,
    "mediaId": 129,
    "date": "5/7/2022 12:00:00 AM",
    "sentence": "Then, last month, <span class='selected-term'>Ron DeSantis</span>, the Republican governor in Florida, took action that threatened to derail that movement: Angry that Bob Chapek, the chief executive of the Walt Disney Company, had spoken out against a Florida law called the Parental Rights in Education act or, by its critics, the Dont Say Gay? law, the governor retaliated.",
    "author": "",
    "title": "Companies Are Stuck Between Their Workers and Politicians"
  },
  {
    "id": 3891,
    "mediaId": 209,
    "date": "5/7/2022 12:00:00 AM",
    "sentence": "",
    "author": "Brigid Kennedy",
    "title": "Texas Gov. Greg Abbott has a controversial plan for the southern border. Is it working?"
  },
  {
    "id": 3867,
    "mediaId": 558,
    "date": "5/8/2022 12:00:00 AM",
    "sentence": "Last month, Floridas governor, <span class='selected-term'>Ron DeSantis</span>, special land use privileges the state gave to Disney for its Disney World theme park in Orlando after the company  responding to backlash from employees and consumers  spoke out against the states dont say gay? law.",
    "author": "Lauren Aratani",
    "title": "Corporate America buckles down for culture war on Roe v Wade"
  },
  {
    "id": 3817,
    "mediaId": 65,
    "date": "5/9/2022 12:00:00 AM",
    "sentence": "",
    "author": "Ronn Blitzer",
    "title": "DeSantis signs bill designating statewide Victims of Communism Day"
  },
  {
    "id": 3821,
    "mediaId": 238,
    "date": "5/9/2022 12:00:00 AM",
    "sentence": "Greg Abbott of Texas and <span class='selected-term'>Ron DeSantis</span> of Florida look likely to win this fall after pushing agendas centered on antipathy to some groups (migrants, transgender Americans) and alignment with others (conservative Christians, rural voters).",
    "author": "",
    "title": "Opinion Trumpism is terrible. It also might be popular."
  },
  {
    "id": 3830,
    "mediaId": 302,
    "date": "5/9/2022 12:00:00 AM",
    "sentence": "",
    "author": "",
    "title": "We need free speech on Florida campuses and critical thinking in the classroom | Column"
  },
  {
    "id": 3832,
    "mediaId": 238,
    "date": "5/9/2022 12:00:00 AM",
    "sentence": "",
    "author": "",
    "title": "DeSantis accused textbooks of indoctrination. Heres what he meant."
  },
  {
    "id": 3839,
    "mediaId": 223,
    "date": "5/9/2022 12:00:00 AM",
    "sentence": "The next GOP president, be it Trump 2.0 or <span class='selected-term'>Ron DeSantis</span> or whoever, needs to hire slowly and fire quickly.",
    "author": "Kurt Schlichter",
    "title": "Yawn  Yet Another Never Trump Loser Sucks Up to the Media"
  },
  {
    "id": 3759,
    "mediaId": 223,
    "date": "5/10/2022 12:00:00 AM",
    "sentence": "Florida's First Lady Casey DeSantis is back on the campaign trail with her husband, Governor <span class='selected-term'>Ron DeSantis</span>, following the completion of her successful cancer treatment.",
    "author": "Spencer Brown",
    "title": "'Damn It Feels Good to Be Here': Casey DeSantis Returns to Campaign Trail"
  },
  {
    "id": 3771,
    "mediaId": 675,
    "date": "5/10/2022 12:00:00 AM",
    "sentence": "",
    "author": "WND News Services",
    "title": "'No more handouts for woke corporations': Disney's special copyright protections could be killed"
  },
  {
    "id": 3773,
    "mediaId": 65,
    "date": "5/10/2022 12:00:00 AM",
    "sentence": "Casey and <span class='selected-term'>Ron DeSantis</span> have been married since 2010.",
    "author": "Kyle Morris",
    "title": "Casey DeSantis returns to campaign trail after battle with breast cancer: 'Damn it feels good to be here'"
  },
  {
    "id": 3774,
    "mediaId": 302,
    "date": "5/10/2022 12:00:00 AM",
    "sentence": "",
    "author": "Jay Cridlin",
    "title": "SBAs Guzman talks keys to small business COVID recovery in Florida, U.S."
  },
  {
    "id": 3788,
    "mediaId": 881,
    "date": "5/10/2022 12:00:00 AM",
    "sentence": "",
    "author": "Paul Blest",
    "title": "Florida teachers cant say gay, but they are required to teach about the victims of communism."
  },
  {
    "id": 3807,
    "mediaId": 129,
    "date": "5/10/2022 12:00:00 AM",
    "sentence": "",
    "author": "",
    "title": "States Turn to Tax Cuts as Inflation Stays Hot"
  },
  {
    "id": 3811,
    "mediaId": 19,
    "date": "5/10/2022 12:00:00 AM",
    "sentence": "",
    "author": "Alana Mastrangelo",
    "title": "Study: Red States Were Right  Schools That Stayed In-Person Didnt Lose Academic Ground"
  },
  {
    "id": 3679,
    "mediaId": 136,
    "date": "5/11/2022 12:00:00 AM",
    "sentence": "A \"race-neutral\" congressional map drawn by Florida Republican Governor <span class='selected-term'>Ron DeSantis</span> that would have eliminated a Black district in a northern part of the state has been struck down by a DeSantis-appointed circuit court judge who found the redistricting plan unconstitutional.",
    "author": "Patricia McKnight",
    "title": "DeSantis-Appointed Judge Blocks His 'Unconstitutional' Redistricting Map"
  },
  {
    "id": 3691,
    "mediaId": 136,
    "date": "5/11/2022 12:00:00 AM",
    "sentence": "In April, <span class='selected-term'>Ron DeSantis</span>, the GOP governor of Florida, signed a bill banning most abortions in the state after 15 weeks of pregnancydown from 24 weeks previously, according to NBC News.",
    "author": "Ed Browne",
    "title": "Roe v. Wade Overturn Could Force Male Birth Control Pill Development"
  },
  {
    "id": 3743,
    "mediaId": 98,
    "date": "5/11/2022 12:00:00 AM",
    "sentence": "",
    "author": "",
    "title": "Roe vs. Wade is doomed. A veteran feminist wonders whats next"
  },
  {
    "id": 3633,
    "mediaId": 132,
    "date": "5/12/2022 12:00:00 AM",
    "sentence": "",
    "author": "Dan Janison",
    "title": "Our built-in state of discord"
  },
  {
    "id": 3634,
    "mediaId": 238,
    "date": "5/12/2022 12:00:00 AM",
    "sentence": "",
    "author": "Paul Waldman",
    "title": "Opinion Trumpism is leaving old-line conservatives behind. Can they catch up?"
  },
  {
    "id": 3653,
    "mediaId": 233,
    "date": "5/12/2022 12:00:00 AM",
    "sentence": "",
    "author": "Jessica Guynn",
    "title": "Proxy season culture war: Republicans urge investors to vote against 'woke' big business like Disney"
  },
  {
    "id": 3604,
    "mediaId": 147,
    "date": "5/13/2022 12:00:00 AM",
    "sentence": "You could be looking  there are any number of scenarios, but you could be looking at a match, say, between the Florida governor, <span class='selected-term'>Ron DeSantis</span>, and, say, Elizabeth Warren of Massachusetts.",
    "author": "PBS NewsHour",
    "title": "Former presidential adviser David Gergen discusses leadership and the next generation"
  },
  {
    "id": 3610,
    "mediaId": 558,
    "date": "5/13/2022 12:00:00 AM",
    "sentence": "Following Disney's (DIS) public battle with Florida Governor <span class='selected-term'>Ron DeSantis</span>, who revoked the company's special tax district after it vowed to help repeal the Parental Rights in Education Act (or what critics have dubbed the \"Don't Say Gay\" bill), the entertainment giant is now fighting another Republican lawmaker.",
    "author": "",
    "title": "Republican-led bill targeting Disney's Mickey Mouse 'can't possibly pass': Lawyer"
  },
  {
    "id": 3611,
    "mediaId": 558,
    "date": "5/13/2022 12:00:00 AM",
    "sentence": "Following Disney's (DIS) public battle with Florida Governor <span class='selected-term'>Ron DeSantis</span>, who revoked the company's special tax district after it vowed to help repeal the Parental Rights in Education Act (or what critics have dubbed the \"Don't Say Gay\" bill), the entertainment giant is now fighting another Republican lawmaker.",
    "author": "",
    "title": "Republican-led bill targeting Disney's Mickey Mouse 'can't possibly pass': Lawyer"
  },
  {
    "id": 3613,
    "mediaId": 302,
    "date": "5/13/2022 12:00:00 AM",
    "sentence": "",
    "author": "",
    "title": "Florida rejected dozens of math textbooks. But only 3 reviewers found CRT violations."
  },
  {
    "id": 3619,
    "mediaId": 157,
    "date": "5/13/2022 12:00:00 AM",
    "sentence": "Apparently, from the view of Governor <span class='selected-term'>Ron DeSantis</span> and Republican legislators who run the state, the sick and dying were too weak to consent and therefore too weak to resist control by ruling elites.",
    "author": "John Stoehr",
    "title": "What does 1 million dead Americans tell us?"
  },
  {
    "id": 3629,
    "mediaId": 19,
    "date": "5/13/2022 12:00:00 AM",
    "sentence": " <span class='selected-term'>Ron DeSantis</span> (@GovRonDeSantis) May 12, 2022\nHis remarks follow news of President Biden canceling oil and gas lease sales in both Alaska and the Gulf of Mexico as Americans continue to feel the pain in their pockets at the gas pump under Bidens leadership.",
    "author": "Hannah Bleau",
    "title": "Ron DeSantis: Joe Bidens Actions Show He Doesnt Care About Rising Gas Prices"
  },
  {
    "id": 3591,
    "mediaId": 238,
    "date": "5/15/2022 12:00:00 AM",
    "sentence": "",
    "author": "",
    "title": "A Glimpse of a Potential Post-Roe Future Through Texas Womens Stories"
  },
  {
    "id": 3537,
    "mediaId": 195,
    "date": "5/16/2022 12:00:00 AM",
    "sentence": "",
    "author": "",
    "title": "How overturning Roe threatens LGBTQ+ rights  faith leaders need to defend them"
  },
  {
    "id": 3538,
    "mediaId": 238,
    "date": "5/16/2022 12:00:00 AM",
    "sentence": "",
    "author": "Michelle Boorstein",
    "title": "Christian nationalism is shaping a Pa. primary  and a GOP shift"
  },
  {
    "id": 3548,
    "mediaId": 195,
    "date": "5/16/2022 12:00:00 AM",
    "sentence": "",
    "author": "",
    "title": "Hawley makes war on business and property rights to score MAGA points"
  },
  {
    "id": 3558,
    "mediaId": 223,
    "date": "5/16/2022 12:00:00 AM",
    "sentence": "",
    "author": "Scott Morefield",
    "title": "The Five Most Important Americans Alive Right Now, And The Missing Elephant In The Room"
  },
  {
    "id": 3559,
    "mediaId": 19,
    "date": "5/16/2022 12:00:00 AM",
    "sentence": "",
    "author": "John Nolte",
    "title": "Nolte: Pro-Grooming Disneys Favorability Rating Plummets 53 Points In One Year"
  },
  {
    "id": 3501,
    "mediaId": 409,
    "date": "5/17/2022 12:00:00 AM",
    "sentence": "The release comes as Disney is embroiled in a fierce controversy over its opposition to House Bill 1557, known as the Parental Rights in Education Bill.? The law, signed by Governor <span class='selected-term'>Ron DeSantis</span> in March of this year, prohibits classroom discussions on gender identity, sexual orientation, and LGBTQ themes in elementary school until Grade 3, and allows parents to sue school districts for non-compliance.",
    "author": "Arjun Singh",
    "title": "Disney Unveils New 2022 Pride Clothing Line for LGBTQ Children"
  },
  {
    "id": 3502,
    "mediaId": 223,
    "date": "5/17/2022 12:00:00 AM",
    "sentence": "Governor <span class='selected-term'>Ron DeSantis</span> (R-FL) signed a bill on Monday barring protesters from picketing at people's homes as pro-abortion demonstrators have shown up to the homes of Supreme Court justices.",
    "author": "Julio Rosas",
    "title": "Ron DeSantis Signs Bill Making It Illegal to Protest at People's Homes"
  },
  {
    "id": 3505,
    "mediaId": 305,
    "date": "5/17/2022 12:00:00 AM",
    "sentence": "Through political figures like Congresswoman Elise Stefanik and Governor <span class='selected-term'>Ron DeSantis</span>.",
    "author": "",
    "title": "Fire Tucker Carlson, Ben Shapiro and All Other Racists Who Promote \"White Replacement Theory\""
  },
  {
    "id": 3525,
    "mediaId": 157,
    "date": "5/17/2022 12:00:00 AM",
    "sentence": "READ MORE: Supreme Court set to give the most extremist movement in the US a big win  and it's not abortion\n<span class='selected-term'>Ron DeSantis</span> and Greg Abbott stood right beside him, pushing through laws to prevent the next generation of potential white terrorists he hoped to influence with his manifesto? from learning the true racial history of America in public schools.",
    "author": "Thom Hartmann",
    "title": "The Buffalo terrorist didn't shoot alone"
  },
  {
    "id": 3470,
    "mediaId": 1546,
    "date": "5/18/2022 12:00:00 AM",
    "sentence": "Not so, according to Florida Governor <span class='selected-term'>Ron DeSantis</span>, a potential 2024 Republican presidential candidate.",
    "author": "Chris Simkins",
    "title": "Looming Midterm Elections Put US Voting Rights in Spotlight"
  },
  {
    "id": 3472,
    "mediaId": 65,
    "date": "5/18/2022 12:00:00 AM",
    "sentence": "",
    "author": "Taylor Penley",
    "title": "Nikole Hannah-Jones, others advocate for critical race theory in wake of Buffalo shooting"
  },
  {
    "id": 3474,
    "mediaId": 223,
    "date": "5/18/2022 12:00:00 AM",
    "sentence": " <span class='selected-term'>Ron DeSantis</span> (@GovRonDeSantis) May 12, 2022",
    "author": "Sarah Arnold",
    "title": "DeSantis: Biden Will Plunge U.S. Into Recession as Gas Prices Soar"
  },
  {
    "id": 3478,
    "mediaId": 406,
    "date": "5/18/2022 12:00:00 AM",
    "sentence": "",
    "author": "Fodor's Travel",
    "title": "Fodor's Travel survey reveals what's freaking out American travelers this summer"
  },
  {
    "id": 3481,
    "mediaId": 305,
    "date": "5/18/2022 12:00:00 AM",
    "sentence": "",
    "author": "Murjani Rawls",
    "title": "Desantis Signs Bill Banning Protests Outside of Residences"
  },
  {
    "id": 3482,
    "mediaId": 881,
    "date": "5/18/2022 12:00:00 AM",
    "sentence": "",
    "author": "David Gilbert",
    "title": "The conferences star attraction will be authoritarian Prime Minister Viktor Orbnthe type of leader former President Trump aspires to be."
  },
  {
    "id": 3493,
    "mediaId": 129,
    "date": "5/18/2022 12:00:00 AM",
    "sentence": "This is the model, in different styles and contexts, of Glenn Youngkin and <span class='selected-term'>Ron DeSantis</span>.",
    "author": "",
    "title": "Americas Doug Mastriano Problem"
  },
  {
    "id": 3463,
    "mediaId": 136,
    "date": "5/19/2022 12:00:00 AM",
    "sentence": "In response to HHS's document, <span class='selected-term'>Ron DeSantis</span>' Florida Department of Health issued guidance of its own clarifying the \"evidence\" HHS/OPA cited.",
    "author": "",
    "title": "HHS Guidance on Trans Pharmacology Raises More Questions Than It Answers | Opinion"
  },
  {
    "id": 7128,
    "mediaId": 136,
    "date": "5/20/2022 12:00:00 AM",
    "sentence": "Florida Governor <span class='selected-term'>Ron DeSantis</span> recently signed a \"Stop Woke Act\" to end Diversity, Equity and Inclusion (DEI) efforts in the workplace.",
    "author": "Summer Rose",
    "title": "Improve the Health of Black Women. Make Racial Trauma at Work Extinct | Opinion"
  },
  {
    "id": 7138,
    "mediaId": 558,
    "date": "5/20/2022 12:00:00 AM",
    "sentence": "In Florida, Governor <span class='selected-term'>Ron DeSantis</span> has moved to use the power of the state to for its stance on gay rights.",
    "author": "Andrew Gawthorpe",
    "title": "Conservatives want to make the US more like Hungary. A terrifying thought"
  },
  {
    "id": 7147,
    "mediaId": 19,
    "date": "5/20/2022 12:00:00 AM",
    "sentence": "",
    "author": "Hannah Bleau",
    "title": "Ron DeSantis: Biden Administration Wants to Punish Americans for Using Carbon with Higher Gas Prices"
  },
  {
    "id": 7153,
    "mediaId": 19,
    "date": "5/20/2022 12:00:00 AM",
    "sentence": "",
    "author": "Hannah Bleau",
    "title": "Ron DeSantis Enhances Drug Trafficking Laws: Bidens Open Border Threatens All Americans Safety"
  },
  {
    "id": 7276,
    "mediaId": 169,
    "date": "5/22/2022 12:00:00 AM",
    "sentence": "",
    "author": "Henry A. Giroux",
    "title": "A new age of fascist politics brings a war on youth  but young people are ready to resist"
  },
  {
    "id": 7278,
    "mediaId": 648,
    "date": "5/22/2022 12:00:00 AM",
    "sentence": "",
    "author": "Andrew Blok",
    "title": "Should You Go Solar if You Live on the East Coast: What You Want to Know"
  },
  {
    "id": 7272,
    "mediaId": 223,
    "date": "5/23/2022 12:00:00 AM",
    "sentence": "If a Youngkin-type, or even a <span class='selected-term'>Ron DeSantis</span> runs and wins the presidency in 2024, these people will not stop.",
    "author": "Will Alexander",
    "title": "Squishy Republicans Want Trump to Go Away"
  }
]