[
  {
    "id": 1444,
    "mediaId": 21,
    "date": "2/7/2022 12:00:00 AM",
    "sentence": "",
    "author": "C. Ryan Barber",
    "title": "Divorce documents provide a rare glimpse into the wealth of Republican Senate candidate David McCormick"
  },
  {
    "id": 1444,
    "mediaId": 21,
    "date": "2/7/2022 12:00:00 AM",
    "sentence": "",
    "author": "C. Ryan Barber",
    "title": "Divorce documents provide a rare glimpse into the wealth of Republican Senate candidate David McCormick"
  }
]