[
  {
    "id": 5877,
    "mediaId": 2643,
    "date": "2022-02-07",
    "sentence": "",
    "author": "Daniel Villarreal",
    "title": "'Hillbilly Elegy' Author's Campaign Suffering Over His Anti-Trump Views"
  },
  {
    "id": 4422,
    "mediaId": 2911,
    "date": "2022-02-28",
    "sentence": "",
    "author": "Kaleigh Rogers",
    "title": "Where Ohio Republicans’ Attacks On Dr. Fauci Came From"
  },
  {
    "id": 3340,
    "mediaId": 2877,
    "date": "2022-03-15",
    "sentence": "",
    "author": "",
    "title": "Trump’s Proposal to Beat the Deep State"
  },
  {
    "id": 2583,
    "mediaId": 2672,
    "date": "2022-03-29",
    "sentence": "",
    "author": "William Vaillancourt",
    "title": "J.D. Vance Says Marjorie Taylor Greene ‘Did Nothing Wrong’ by Speaking at White Nationalist Rally"
  },
  {
    "id": 1918,
    "mediaId": 2664,
    "date": "2022-03-29",
    "sentence": "",
    "author": "",
    "title": "GOP Senate candidates ignore real issues facing Ohioans to put on repugnant political circus"
  }
]