{
  "id": 5322,
  "mediaId": 2687,
  "date": "2022-04-12",
  "headline": "Pennsylvania GOP Will Nominate a Crackpot for Governor",
  "image": "https://politicalwire.com/wp-content/uploads/2018/02/PW-podcast-logo.jpg",
  "link": "https://politicalwire.com/2022/04/12/pennsylvania-gop-will-nominate-a-crackpot-for-governor/",
  "mediaOutlet": "Taegan Goddard's Political Wire",
  "biasRatingId": 1,
  "wordCount": 0,
  "author": "Taegan Goddard",
  "authorUrl": "https://politicalwire.com/author/tdg/",
  "termIds": [
    4222,
    1126,
    1489,
    1131,
    6506
  ],
  "sentences": [
    "Amanda Carpenter: “LOL, if you thought Donald Trump’s endorsement of Dr. Mehmet Oz for Senate was the worst development in Pennsylvania’s 2022 GOP primaries, wait until you hear about the Republicans running for governor.”\n“Pennsylvania Republicans will nominate a 2020 election conspiracist for governor in the May 17 primary.",
    "And, there’s an excellent chance the nuttiest bunny of them all, Doug Mastriano, is going to win the primary.”\n“Which means that Republicans might get a crackpot governing this swing state in 2024.",
    "The only thing differentiating them is how far down the rabbit hole they go.",
    "What could possibly go wrong?”\nSave to Favorites",
    "Because they’re all election conspiracists.",
    "How can I be sure of that?"
  ]
}