[
  {
    "id": 2449,
    "mediaId": 43,
    "date": "1/1/2022 12:00:00 AM",
    "sentence": "Let's show them we're NOT backing down: https://t.co/4OXYM6kWP5 pic.twitter.com/o6xQ538lJz\n <span class='selected-term'>Mandela Barnes</span> (@TheOtherMandela) December 20, 2021",
    "author": "",
    "title": "The way forward is to view Manchin and Sinema as opportunities not just as obstacles"
  },
  {
    "id": 2449,
    "mediaId": 43,
    "date": "1/1/2022 12:00:00 AM",
    "sentence": "Let's show them we're NOT backing down: https://t.co/4OXYM6kWP5 pic.twitter.com/o6xQ538lJz\n <span class='selected-term'>Mandela Barnes</span> (@TheOtherMandela) December 20, 2021",
    "author": "",
    "title": "The way forward is to view Manchin and Sinema as opportunities not just as obstacles"
  },
  {
    "id": 2442,
    "mediaId": 124,
    "date": "1/6/2022 12:00:00 AM",
    "sentence": "",
    "author": "",
    "title": "Biden gives Democrats the anti-Trump speech they've been waiting for"
  },
  {
    "id": 2442,
    "mediaId": 124,
    "date": "1/6/2022 12:00:00 AM",
    "sentence": "",
    "author": "",
    "title": "Biden gives Democrats the anti-Trump speech they've been waiting for"
  },
  {
    "id": 2440,
    "mediaId": 367,
    "date": "1/7/2022 12:00:00 AM",
    "sentence": "",
    "author": "Bill Glauber",
    "title": "U.S. Sen. Ron Johnson poised to announce run for a third term as early as next week, according to sources"
  },
  {
    "id": 2440,
    "mediaId": 367,
    "date": "1/7/2022 12:00:00 AM",
    "sentence": "",
    "author": "Bill Glauber",
    "title": "U.S. Sen. Ron Johnson poised to announce run for a third term as early as next week, according to sources"
  },
  {
    "id": 2436,
    "mediaId": 21,
    "date": "1/8/2022 12:00:00 AM",
    "sentence": "",
    "author": "John L. Dorman",
    "title": "GOP Sen. Ron Johnson of Wisconsin, a top foil for Democrats who pledged to only serve for two terms, poised to run for reelection to a third: sources"
  },
  {
    "id": 2436,
    "mediaId": 21,
    "date": "1/8/2022 12:00:00 AM",
    "sentence": "",
    "author": "John L. Dorman",
    "title": "GOP Sen. Ron Johnson of Wisconsin, a top foil for Democrats who pledged to only serve for two terms, poised to run for reelection to a third: sources"
  },
  {
    "id": 2422,
    "mediaId": 147,
    "date": "1/9/2022 12:00:00 AM",
    "sentence": "",
    "author": "Scott Bauer",
    "title": "Wisconsin Republican Sen. Ron Johnson will seek reelection"
  },
  {
    "id": 2424,
    "mediaId": 312,
    "date": "1/9/2022 12:00:00 AM",
    "sentence": "",
    "author": "SCOTT BAUER / AP",
    "title": "Wisconsin Republican Sen. Ron Johnson Will Seek Reelection"
  },
  {
    "id": 2432,
    "mediaId": 124,
    "date": "1/9/2022 12:00:00 AM",
    "sentence": "",
    "author": "",
    "title": "GOP Sen. Ron Johnson announces bid for third term in Wisconsin"
  },
  {
    "id": 2435,
    "mediaId": 178,
    "date": "1/9/2022 12:00:00 AM",
    "sentence": "",
    "author": "SCOTT BAUER",
    "title": "Wisconsin Republican Sen. Ron Johnson will seek reelection"
  },
  {
    "id": 2422,
    "mediaId": 147,
    "date": "1/9/2022 12:00:00 AM",
    "sentence": "",
    "author": "Scott Bauer",
    "title": "Wisconsin Republican Sen. Ron Johnson will seek reelection"
  },
  {
    "id": 2424,
    "mediaId": 312,
    "date": "1/9/2022 12:00:00 AM",
    "sentence": "",
    "author": "SCOTT BAUER / AP",
    "title": "Wisconsin Republican Sen. Ron Johnson Will Seek Reelection"
  },
  {
    "id": 2432,
    "mediaId": 124,
    "date": "1/9/2022 12:00:00 AM",
    "sentence": "",
    "author": "",
    "title": "GOP Sen. Ron Johnson announces bid for third term in Wisconsin"
  },
  {
    "id": 2435,
    "mediaId": 178,
    "date": "1/9/2022 12:00:00 AM",
    "sentence": "",
    "author": "SCOTT BAUER",
    "title": "Wisconsin Republican Sen. Ron Johnson will seek reelection"
  },
  {
    "id": 2420,
    "mediaId": 112,
    "date": "1/10/2022 12:00:00 AM",
    "sentence": "",
    "author": "Associated Press",
    "title": "Wisconsin Republican Ron Johnson to run for re-election to Senate, reversing self-imposed term-limit vow"
  },
  {
    "id": 2420,
    "mediaId": 112,
    "date": "1/10/2022 12:00:00 AM",
    "sentence": "",
    "author": "Associated Press",
    "title": "Wisconsin Republican Ron Johnson to run for re-election to Senate, reversing self-imposed term-limit vow"
  },
  {
    "id": 2398,
    "mediaId": 178,
    "date": "1/25/2022 12:00:00 AM",
    "sentence": "",
    "author": "SCOTT BAUER",
    "title": "US Senate candidate Godlewski unveils rural Wisconsin plan"
  },
  {
    "id": 2398,
    "mediaId": 178,
    "date": "1/25/2022 12:00:00 AM",
    "sentence": "",
    "author": "SCOTT BAUER",
    "title": "US Senate candidate Godlewski unveils rural Wisconsin plan"
  },
  {
    "id": 2394,
    "mediaId": 367,
    "date": "1/31/2022 12:00:00 AM",
    "sentence": "",
    "author": "Bill Glauber",
    "title": "Democratic U.S. Senate candidate Alex Lasry pours in $1.55 million more into race, while Sarah Godlewski adds $750,000"
  },
  {
    "id": 2394,
    "mediaId": 367,
    "date": "1/31/2022 12:00:00 AM",
    "sentence": "",
    "author": "Bill Glauber",
    "title": "Democratic U.S. Senate candidate Alex Lasry pours in $1.55 million more into race, while Sarah Godlewski adds $750,000"
  },
  {
    "id": 2387,
    "mediaId": 367,
    "date": "2/21/2022 12:00:00 AM",
    "sentence": "Not only does <span class='selected-term'>Mandela Barnes</span> oppose holding bad actors like John Chisholm accountable, but he wants to enable more violent criminals like Darrell Brooks to walk free via reckless cash bail policies,\" said Anna Kelly, spokeswoman for the Republican Party.",
    "author": "Daniel Bice",
    "title": "Bice: U.S. Senate candidate Mandela Barnes favors eliminating cash bail nationally, aide says"
  },
  {
    "id": 2387,
    "mediaId": 367,
    "date": "2/21/2022 12:00:00 AM",
    "sentence": "Not only does <span class='selected-term'>Mandela Barnes</span> oppose holding bad actors like John Chisholm accountable, but he wants to enable more violent criminals like Darrell Brooks to walk free via reckless cash bail policies,\" said Anna Kelly, spokeswoman for the Republican Party.",
    "author": "Daniel Bice",
    "title": "Bice: U.S. Senate candidate Mandela Barnes favors eliminating cash bail nationally, aide says"
  },
  {
    "id": 2386,
    "mediaId": 367,
    "date": "2/23/2022 12:00:00 AM",
    "sentence": "More:<span class='selected-term'>Mandela Barnes</span> raises $1.23 million during last 3 months of 2021 in Wisconsin U.S. Senate race\nIn joining the state treasurer race, Battino is expected to build on what she learned on the campaign trail over the past year, with voters raising concerns about such issues as rural broadband, health care and financial insecurity.",
    "author": "Bill Glauber",
    "title": "Gillian Battino expected to leave Democratic U.S. Senate race and announce run for state treasurer"
  },
  {
    "id": 2386,
    "mediaId": 367,
    "date": "2/23/2022 12:00:00 AM",
    "sentence": "More:<span class='selected-term'>Mandela Barnes</span> raises $1.23 million during last 3 months of 2021 in Wisconsin U.S. Senate race\nIn joining the state treasurer race, Battino is expected to build on what she learned on the campaign trail over the past year, with voters raising concerns about such issues as rural broadband, health care and financial insecurity.",
    "author": "Bill Glauber",
    "title": "Gillian Battino expected to leave Democratic U.S. Senate race and announce run for state treasurer"
  },
  {
    "id": 2385,
    "mediaId": 367,
    "date": "2/24/2022 12:00:00 AM",
    "sentence": "",
    "author": "Bill Glauber",
    "title": "'Voters don't know where he's at': Tom Nelson turns sights on Democratic rival Mandela Barnes in U.S. Senate race"
  },
  {
    "id": 2385,
    "mediaId": 367,
    "date": "2/24/2022 12:00:00 AM",
    "sentence": "",
    "author": "Bill Glauber",
    "title": "'Voters don't know where he's at': Tom Nelson turns sights on Democratic rival Mandela Barnes in U.S. Senate race"
  },
  {
    "id": 2378,
    "mediaId": 367,
    "date": "3/2/2022 12:00:00 AM",
    "sentence": "",
    "author": "Bill Glauber",
    "title": "Marquette poll shows Rebecca Kleefisch and Mandela Barnes leading key primary contests"
  },
  {
    "id": 2378,
    "mediaId": 367,
    "date": "3/2/2022 12:00:00 AM",
    "sentence": "",
    "author": "Bill Glauber",
    "title": "Marquette poll shows Rebecca Kleefisch and Mandela Barnes leading key primary contests"
  },
  {
    "id": 2349,
    "mediaId": 367,
    "date": "3/24/2022 12:00:00 AM",
    "sentence": "",
    "author": "Bill Glauber",
    "title": "Democratic U.S. Senate contenders in Wisconsin focus on manufacturing"
  },
  {
    "id": 2349,
    "mediaId": 367,
    "date": "3/24/2022 12:00:00 AM",
    "sentence": "",
    "author": "Bill Glauber",
    "title": "Democratic U.S. Senate contenders in Wisconsin focus on manufacturing"
  },
  {
    "id": 2346,
    "mediaId": 21,
    "date": "3/29/2022 12:00:00 AM",
    "sentence": "AP Photo/Morry Gash\n<span class='selected-term'>Mandela Barnes</span> has a 21-point lead in the Wisconsin Senate Democratic primary, per an internal poll.",
    "author": "John L. Dorman",
    "title": "Wisconsin Lt. Gov. Mandela Barnes has early lead in Democratic Senate primary: poll"
  },
  {
    "id": 2346,
    "mediaId": 21,
    "date": "3/29/2022 12:00:00 AM",
    "sentence": "AP Photo/Morry Gash\n<span class='selected-term'>Mandela Barnes</span> has a 21-point lead in the Wisconsin Senate Democratic primary, per an internal poll.",
    "author": "John L. Dorman",
    "title": "Wisconsin Lt. Gov. Mandela Barnes has early lead in Democratic Senate primary: poll"
  },
  {
    "id": 2337,
    "mediaId": 367,
    "date": "4/12/2022 12:00:00 AM",
    "sentence": "Democratic U.S. Senate candidate <span class='selected-term'>Mandela Barnes</span> is breaking with the Biden administration on a key piece of immigration policy.",
    "author": "Bill Glauber",
    "title": "Democratic U.S. Senate candidate Mandela Barnes opposes Biden administration's plan to lift Title 42 rule at the border"
  },
  {
    "id": 2337,
    "mediaId": 367,
    "date": "4/12/2022 12:00:00 AM",
    "sentence": "Democratic U.S. Senate candidate <span class='selected-term'>Mandela Barnes</span> is breaking with the Biden administration on a key piece of immigration policy.",
    "author": "Bill Glauber",
    "title": "Democratic U.S. Senate candidate Mandela Barnes opposes Biden administration's plan to lift Title 42 rule at the border"
  },
  {
    "id": 2332,
    "mediaId": 238,
    "date": "4/13/2022 12:00:00 AM",
    "sentence": "",
    "author": "",
    "title": "Opinion: Democrats must make a strategic choice in Wisconsin's Senate race"
  },
  {
    "id": 2335,
    "mediaId": 367,
    "date": "4/13/2022 12:00:00 AM",
    "sentence": "More:Democratic U.S. Senate candidate <span class='selected-term'>Mandela Barnes</span> opposes Biden administration's plan to lift Title 42 rule at the border\nMore:Democratic U.S. Senate candidate Sarah Godlewski issues 'Cut Costs Plan,' calls for suspension of federal gas tax",
    "author": "Bill Glauber",
    "title": "Democratic U.S. Senate contender Alex Lasry vows to 'bring more jobs and investment back to rural Wisconsin'"
  },
  {
    "id": 2332,
    "mediaId": 238,
    "date": "4/13/2022 12:00:00 AM",
    "sentence": "",
    "author": "",
    "title": "Opinion: Democrats must make a strategic choice in Wisconsin's Senate race"
  },
  {
    "id": 2335,
    "mediaId": 367,
    "date": "4/13/2022 12:00:00 AM",
    "sentence": "More:Democratic U.S. Senate candidate <span class='selected-term'>Mandela Barnes</span> opposes Biden administration's plan to lift Title 42 rule at the border\nMore:Democratic U.S. Senate candidate Sarah Godlewski issues 'Cut Costs Plan,' calls for suspension of federal gas tax",
    "author": "Bill Glauber",
    "title": "Democratic U.S. Senate contender Alex Lasry vows to 'bring more jobs and investment back to rural Wisconsin'"
  },
  {
    "id": 2326,
    "mediaId": 367,
    "date": "4/15/2022 12:00:00 AM",
    "sentence": "",
    "author": "Bill Glauber",
    "title": "Republican U.S. Sen. Ron Johnson raised $7.1 million in campaign cash during the first three months of 2022"
  },
  {
    "id": 2326,
    "mediaId": 367,
    "date": "4/15/2022 12:00:00 AM",
    "sentence": "",
    "author": "Bill Glauber",
    "title": "Republican U.S. Sen. Ron Johnson raised $7.1 million in campaign cash during the first three months of 2022"
  },
  {
    "id": 2314,
    "mediaId": 147,
    "date": "4/17/2022 12:00:00 AM",
    "sentence": "CAMBRIDGE, Wis. (AP)  Among the red barns, bins and tractors of a southern Wisconsin dairy farm, Democratic U.S. Senate candidate <span class='selected-term'>Mandela Barnes</span> sat at a white picnic table painted with black spots to resemble a dairy cow.",
    "author": "Scott Bauer",
    "title": "Wisconsin Democrats search for strategy to unseat GOP Sen. Ron Johnson"
  },
  {
    "id": 2314,
    "mediaId": 147,
    "date": "4/17/2022 12:00:00 AM",
    "sentence": "CAMBRIDGE, Wis. (AP)  Among the red barns, bins and tractors of a southern Wisconsin dairy farm, Democratic U.S. Senate candidate <span class='selected-term'>Mandela Barnes</span> sat at a white picnic table painted with black spots to resemble a dairy cow.",
    "author": "Scott Bauer",
    "title": "Wisconsin Democrats search for strategy to unseat GOP Sen. Ron Johnson"
  },
  {
    "id": 2310,
    "mediaId": 367,
    "date": "4/21/2022 12:00:00 AM",
    "sentence": "",
    "author": "Bill Glauber",
    "title": "Democratic U.S. Senate candidate Steven Olikara unveils 'agenda to make government work'"
  },
  {
    "id": 2310,
    "mediaId": 367,
    "date": "4/21/2022 12:00:00 AM",
    "sentence": "",
    "author": "Bill Glauber",
    "title": "Democratic U.S. Senate candidate Steven Olikara unveils 'agenda to make government work'"
  },
  {
    "id": 2304,
    "mediaId": 195,
    "date": "4/27/2022 12:00:00 AM",
    "sentence": "",
    "author": "Tal Axelrod",
    "title": "Democratic Senate primary tightening in Wisconsin: poll"
  },
  {
    "id": 2306,
    "mediaId": 367,
    "date": "4/27/2022 12:00:00 AM",
    "sentence": "",
    "author": "Bill Glauber",
    "title": "Marquette Poll shows Mandela Barnes, Alex Lasry in tight Democratic U.S. Senate race in Wisconsin"
  },
  {
    "id": 2306,
    "mediaId": 367,
    "date": "4/27/2022 12:00:00 AM",
    "sentence": "",
    "author": "Bill Glauber",
    "title": "Marquette Poll shows Mandela Barnes, Alex Lasry in tight Democratic U.S. Senate race in Wisconsin"
  },
  {
    "id": 2304,
    "mediaId": 195,
    "date": "4/27/2022 12:00:00 AM",
    "sentence": "",
    "author": "Tal Axelrod",
    "title": "Democratic Senate primary tightening in Wisconsin: poll"
  },
  {
    "id": 2302,
    "mediaId": 238,
    "date": "4/28/2022 12:00:00 AM",
    "sentence": "As I have written, the leading Democratic Senate contender, <span class='selected-term'>Mandela Barnes</span>, initially went far to the left (e.g., favoring Medicare-for-all, abolishing ICE), although he recently has tried to tack back to the center.",
    "author": "",
    "title": "Opinion The Wisconsin GOP is stuck with Ron Johnson. Democrats could pick a winner."
  },
  {
    "id": 2303,
    "mediaId": 151,
    "date": "4/28/2022 12:00:00 AM",
    "sentence": "",
    "author": "",
    "title": "Pro-Bernie group endorses in key Dem Senate primary"
  },
  {
    "id": 2302,
    "mediaId": 238,
    "date": "4/28/2022 12:00:00 AM",
    "sentence": "As I have written, the leading Democratic Senate contender, <span class='selected-term'>Mandela Barnes</span>, initially went far to the left (e.g., favoring Medicare-for-all, abolishing ICE), although he recently has tried to tack back to the center.",
    "author": "",
    "title": "Opinion The Wisconsin GOP is stuck with Ron Johnson. Democrats could pick a winner."
  },
  {
    "id": 2303,
    "mediaId": 151,
    "date": "4/28/2022 12:00:00 AM",
    "sentence": "",
    "author": "",
    "title": "Pro-Bernie group endorses in key Dem Senate primary"
  },
  {
    "id": 2301,
    "mediaId": 367,
    "date": "4/29/2022 12:00:00 AM",
    "sentence": "",
    "author": "Bill Glauber",
    "title": "Wisconsin U.S. Senate election updates: Tom Nelson claims endorsement from Bernie Sanders-linked Our Wisconsin Revolution"
  },
  {
    "id": 2301,
    "mediaId": 367,
    "date": "4/29/2022 12:00:00 AM",
    "sentence": "",
    "author": "Bill Glauber",
    "title": "Wisconsin U.S. Senate election updates: Tom Nelson claims endorsement from Bernie Sanders-linked Our Wisconsin Revolution"
  }
]