[
  {
    "id": 1974,
    "mediaId": 2658,
    "date": "2022-02-06",
    "sentence": "",
    "author": "",
    "title": "POLITICO Playbook: A Manchin-Murkowski mindmeld"
  },
  {
    "id": 11665,
    "mediaId": 2745,
    "date": "2022-03-25",
    "sentence": "",
    "author": "",
    "title": "How senators voted on Ketanji Brown Jackson for the Supreme Court"
  },
  {
    "id": 12232,
    "mediaId": 2526,
    "date": "2022-03-27",
    "sentence": "Kyrsten Sinema (D-AZ) and <span class='selected-term'>Mark Kelly</span> (D-AZ).",
    "author": "John Binder",
    "title": "Senate GOP Moderates Silent on Ketanji Brown Jackson’s Trustee Role at Woke, Pro-Critical Race Theory School"
  },
  {
    "id": 9795,
    "mediaId": 2572,
    "date": "2022-04-01",
    "sentence": "",
    "author": "Tyler Olson",
    "title": "Democratic Sens. Kelly, Manchin press Biden over Gulf oil leases"
  },
  {
    "id": 9802,
    "mediaId": 2572,
    "date": "2022-04-04",
    "sentence": "Sen. <span class='selected-term'>Mark Kelly</span>, D-Ariz., Monday became the latest Democrat to officially back Jackson.",
    "author": "Tyler Olson",
    "title": "Judiciary panel deadlocks on Jackson SCOTUS nomination, setting up Senate vote to move it out of committee"
  },
  {
    "id": 6341,
    "mediaId": 2658,
    "date": "2022-04-18",
    "sentence": "Democrats are defending four incumbents in closely contested states: Hassan, Warnock, Nevada Sen. Catherine Cortez Masto and Sen. <span class='selected-term'>Mark Kelly</span> in Arizona.",
    "author": "",
    "title": "McConnell-tied super PAC makes early $141M play for the Senate"
  },
  {
    "id": 4953,
    "mediaId": 2589,
    "date": "2022-04-18",
    "sentence": "",
    "author": "Ed Morrissey",
    "title": "How will McConnell survive as Senate GOP leader? Here are 141 million reasons ..."
  }
]