[
  {
    "id": 26178,
    "mediaId": 2886,
    "date": "2022-02-23",
    "sentence": "",
    "author": "",
    "title": "On Borders Worth Defending"
  },
  {
    "id": 26385,
    "mediaId": 2810,
    "date": "2022-02-25",
    "sentence": "",
    "author": "Elie Mystal",
    "title": "Biden Has Chosen Ketanji Brown Jackson for a Reason"
  },
  {
    "id": 26414,
    "mediaId": 2548,
    "date": "2022-03-07",
    "sentence": "",
    "author": "Michael Ginsberg",
    "title": "Gubernatorial Candidate Anthony Trimino Explains Why California Is Ready For A GOP Takeover"
  },
  {
    "id": 25736,
    "mediaId": 2810,
    "date": "2022-04-13",
    "sentence": "",
    "author": "John Nichols",
    "title": "What J.D. Vance Doesn’t Know About France"
  }
]