[
  {
    "id": 23,
    "mediaId": 195,
    "date": "4/5/2022 12:00:00 AM",
    "sentence": "Rep. <span class='selected-term'>Peter Meijer</span> (R-Mich.) faces John Gibbs, a former Trump administration official.",
    "author": "Cristina Marcos",
    "title": "Veteran lawmaker's exit has House GOP trending toward Trump"
  },
  {
    "id": 24,
    "mediaId": 238,
    "date": "4/5/2022 12:00:00 AM",
    "sentence": "and <span class='selected-term'>Peter Meijer</span> (Mich.)  face tough primary challenges.",
    "author": "Amy B Wang",
    "title": "GOP Rep. Upton, who voted to impeach Trump, will not seek reelection"
  },
  {
    "id": 26,
    "mediaId": 261,
    "date": "4/5/2022 12:00:00 AM",
    "sentence": "Also voting to impeach was U.S. Rep. <span class='selected-term'>Peter Meijer</span>, R-Grand Rapids, who is running for reelection this year despite Trump's endorsement of another candidate, John Gibbs.",
    "author": "Todd Spangler",
    "title": "Rep. Fred Upton announces retirement from Congress, has been in US House since 1987"
  },
  {
    "id": 27,
    "mediaId": 238,
    "date": "4/5/2022 12:00:00 AM",
    "sentence": "and <span class='selected-term'>Peter Meijer</span> (Mich.)  face tough primary challenges.",
    "author": "",
    "title": "GOP Rep. Upton, who voted to impeach Trump, will not seek reelection"
  }
]