{
  "id": 14201,
  "mediaId": 8399,
  "date": "2022-03-17",
  "headline": "After Hours: Natalie Bencivenga interviews Josh Shapiro",
  "image": "https://media1.fdncms.com/pittsburgh/imager/u/slideshow/21305880/after-hours-josh-shapiro-teaser.jpg",
  "link": "https://www.pghcitypaper.com/pittsburgh/after-hours-natalie-bencivenga-interviews-josh-shapiro/Content?oid=21305606",
  "mediaOutlet": "pghcitypaper.com",
  "biasRatingId": 1,
  "wordCount": 0,
  "author": "Natalie Bencivenga",
  "authorUrl": "https://www.pghcitypaper.com/author/natalie-bencivenga",
  "termIds": [
    3926,
    1022,
    6506
  ],
  "sentences": [
    "Tune in as they discuss fracking, policing, what lessons he’s learned from the work he’s done, and why he says he rejects labels in favor of working towards unity with all Pennsylvanians.",
    "After Hours host Natalie Bencivenga interviews Josh Shapiro, Pa. Attorney General of Pennsylvania, who is running for Governor of Pennsylvania."
  ]
}