[
  {
    "id": 6617,
    "mediaId": 323,
    "date": "5/18/2022 12:00:00 AM",
    "sentence": "Plus, Pennsylvania Republicans nominate <span class='selected-term'>Doug Mastriano</span> for Governor, while progressive candidates surge, and Rep. Madison Cawthorn loses after becoming plagued by scandal.Read Transcript\nAD\nLoading advertisement...\n00:00\n1x\nSubscribe\nApple Podcasts\nGoogle Podcasts\nSpotify\niHeartRadio\nTuneIn\nStitcher\nAmazon Alexa\nRSS\nOnly three weeks after that announcement, media reports say the board is being paused? and Ms. Jankowicz has resigned.",
    "author": "The Editorial Board",
    "title": "The Disinformation Governance Board, Disavowed"
  }
]