[
  {
    "id": 3624,
    "mediaId": 2590,
    "date": "2022-01-18",
    "sentence": "",
    "author": "Liz Skalka",
    "title": "Inside J.D. Vance's Possibly B.S. 'No B.S. Tour' Across Ohio"
  },
  {
    "id": 3607,
    "mediaId": 2550,
    "date": "2022-01-21",
    "sentence": "",
    "author": "",
    "title": "It's starting to occur to Trump that some of his endorsements have proven subpar"
  },
  {
    "id": 3559,
    "mediaId": 2658,
    "date": "2022-01-21",
    "sentence": "",
    "author": "",
    "title": "‘Crypto bros,’ UFOs and NFTs: Inside Peter Thiel’s Senate fundraising tour"
  },
  {
    "id": 2146,
    "mediaId": 2699,
    "date": "2022-02-04",
    "sentence": "",
    "author": "Asawin Suebsaeng",
    "title": "Trump Fixated on ‘Fucking Weird’ Senate Candidate and His Sex Life"
  },
  {
    "id": 2260,
    "mediaId": 2912,
    "date": "2022-02-07",
    "sentence": "",
    "author": "",
    "title": "Peter Thiel to exit board of Facebook parent Meta to support Trump-aligned candidates"
  },
  {
    "id": 1909,
    "mediaId": 2564,
    "date": "2022-02-07",
    "sentence": "",
    "author": "Adam Manno For Dailymail.Com",
    "title": "Facebook angel investor Peter Thiel steps down from the social media giant's board after 17 years to back GOP candidates JD Vance and Blake Masters for US Senate: Follows disastrous day for Meta which saw stocks plunge by 26%"
  },
  {
    "id": 2129,
    "mediaId": 6598,
    "date": "2022-02-07",
    "sentence": "",
    "author": "",
    "title": "Peter Thiel to Exit Meta’s Board to Support Trump-Aligned Candidates"
  },
  {
    "id": 2068,
    "mediaId": 2712,
    "date": "2022-02-07",
    "sentence": "",
    "author": "Patrick Knox",
    "title": "What is the Rumble app?"
  },
  {
    "id": 1893,
    "mediaId": 2664,
    "date": "2022-02-07",
    "sentence": "",
    "author": "Brad Reed",
    "title": "Peter Thiel stepping down from Facebook board to help elect Trump-loving candidates: NYT"
  },
  {
    "id": 1811,
    "mediaId": 2658,
    "date": "2022-02-07",
    "sentence": "",
    "author": "",
    "title": "'Precipitous decline': J.D. Vance pollster issues warning on Ohio Senate race"
  },
  {
    "id": 1827,
    "mediaId": 8491,
    "date": "2022-02-07",
    "sentence": "",
    "author": "",
    "title": "Trump 2020 campaign chief to advise Gibbons in Ohio Senate race"
  },
  {
    "id": 2362,
    "mediaId": 2643,
    "date": "2022-02-07",
    "sentence": "",
    "author": "Adam Staten",
    "title": "PayPal Co-Founder Peter Thiel Stepping Down From Meta's Board"
  },
  {
    "id": 2502,
    "mediaId": 2630,
    "date": "2022-02-07",
    "sentence": "",
    "author": "",
    "title": "Republican donor and investor Peter Thiel to leave Facebook board"
  },
  {
    "id": 2465,
    "mediaId": 2819,
    "date": "2022-02-07",
    "sentence": "",
    "author": "Megan McCluskey",
    "title": "Thiel-Backed Video Platform Rumble Offers Joe Rogan $100 Million to Switch From Spotify"
  },
  {
    "id": 2118,
    "mediaId": 4011,
    "date": "2022-02-07",
    "sentence": "",
    "author": "",
    "title": "'A New Era': Peter Thiel Steps Down From Meta's Board of Directors"
  },
  {
    "id": 2526,
    "mediaId": 2510,
    "date": "2022-02-08",
    "sentence": "",
    "author": "Alex Cooper",
    "title": "Gay Billionaire Peter Thiel Exits Meta Board to Fund Trump Candidates"
  },
  {
    "id": 2318,
    "mediaId": 2522,
    "date": "2022-02-08",
    "sentence": "",
    "author": "BPR Wire",
    "title": "Peter Thiel will step down from role at Facebook parent company, reportedly to elect Trump-friendly candidates"
  },
  {
    "id": 2533,
    "mediaId": 2540,
    "date": "2022-02-09",
    "sentence": "",
    "author": "Clare Duffy and Brian Fung",
    "title": "Peter Thiel is backing a new generation of Trump-aligned Republicans"
  },
  {
    "id": 1975,
    "mediaId": 2553,
    "date": "2022-02-10",
    "sentence": "",
    "author": "Tim Pearce",
    "title": "Silicon Valley Mega Investor Leaving Meta’s Board For GOP Politics: Report"
  },
  {
    "id": 13349,
    "mediaId": 2510,
    "date": "2022-02-28",
    "sentence": "",
    "author": "Jacob Ogles",
    "title": "Did Milo Connect Marjorie Taylor Greene With a Racist Fla. Convention?"
  },
  {
    "id": 10824,
    "mediaId": 2573,
    "date": "2022-03-07",
    "sentence": "",
    "author": "Paul Steinhauser",
    "title": "Ohio GOP Senate showdown: Super PAC spotlights for J.D. Vance, ‘border security is personal’"
  },
  {
    "id": 10755,
    "mediaId": 2664,
    "date": "2022-03-18",
    "sentence": "",
    "author": "Sarah K. Burris",
    "title": "JD Vance's hapless senate campaign destroyed after ‘electorally stupid’ Ukraine comment: conservative"
  },
  {
    "id": 11119,
    "mediaId": 2745,
    "date": "2022-03-18",
    "sentence": "",
    "author": "",
    "title": "Opinion: Why is J.D. Vance getting canceled by his fellow Republicans?"
  },
  {
    "id": 9772,
    "mediaId": 2918,
    "date": "2022-03-21",
    "sentence": "",
    "author": "Simone Hanna",
    "title": "Neocon ‘Bulwark’ Blog Lies About J.D. Vance ‘Cancellation’ After Senate Candidate Dismisses ‘Ukraine First’ Ideology."
  },
  {
    "id": 9276,
    "mediaId": 2625,
    "date": "2022-03-22",
    "sentence": "",
    "author": "Jacob Rosenberg",
    "title": "Here’s a Helpful Video Explaining Republicans’ 2022 Policy Agenda"
  },
  {
    "id": 9233,
    "mediaId": 2636,
    "date": "2022-03-22",
    "sentence": "",
    "author": "",
    "title": "The Rise of the Tucker Carlson Politician"
  },
  {
    "id": 9189,
    "mediaId": 2547,
    "date": "2022-03-23",
    "sentence": "",
    "author": "Steve M.",
    "title": "REALLY? New York Times Shocked By Winger Political Practices"
  },
  {
    "id": 7459,
    "mediaId": 2875,
    "date": "2022-04-01",
    "sentence": "",
    "author": "Derek Royden",
    "title": "NatCon kingmaker?"
  },
  {
    "id": 6096,
    "mediaId": 2671,
    "date": "2022-04-20",
    "sentence": "",
    "author": "The Right Scoop",
    "title": "Don Jr. explains why Trump endorsed JD Vance… [UPDATE: PETER THIEL INVOLVED TOO]"
  },
  {
    "id": 5929,
    "mediaId": 2741,
    "date": "2022-04-20",
    "sentence": "",
    "author": "James Pogue",
    "title": "Inside the New Right, Where Peter Thiel Is Placing His Biggest Bets"
  },
  {
    "id": 5405,
    "mediaId": 2557,
    "date": "2022-04-20",
    "sentence": "",
    "author": "DML News App",
    "title": "REPORT: Trump-Endorsed Senate Candidate Receives Mega Donation From Conservative Billionaire"
  },
  {
    "id": 5404,
    "mediaId": 2687,
    "date": "2022-04-20",
    "sentence": "",
    "author": "Taegan Goddard",
    "title": "Peter Thiel Convinced Trump to Endorse J.D. Vance"
  },
  {
    "id": 5392,
    "mediaId": 2641,
    "date": "2022-04-21",
    "sentence": "",
    "author": "Eric Mack",
    "title": "Donald Trump Jr., Vance-Backing PAC Blast Mandel for Establishment Ties"
  },
  {
    "id": 5470,
    "mediaId": 2676,
    "date": "2022-04-22",
    "sentence": "",
    "author": "Igor Derysh",
    "title": "“Go f**k yourself”: Trump and Don Jr. war with top GOP donor who bought ads opposing his candidate"
  },
  {
    "id": 5481,
    "mediaId": 2741,
    "date": "2022-04-22",
    "sentence": "",
    "author": "Emily Jane Fox",
    "title": "“Conservative Guys Are Going to Get All the Girls”: Author James Pogue on the New Right"
  },
  {
    "id": 5378,
    "mediaId": 2664,
    "date": "2022-04-22",
    "sentence": "",
    "author": "Igor Derysh",
    "title": "Trump and Don Jr. go to war with top GOP donor who bought ads opposing his candidate"
  },
  {
    "id": 6099,
    "mediaId": 2716,
    "date": "2022-04-22",
    "sentence": "",
    "author": "Samuel Goldman",
    "title": "The new right isn't conservative. They don't want to be."
  },
  {
    "id": 4767,
    "mediaId": 2512,
    "date": "2022-04-23",
    "sentence": "",
    "author": "Meaghan Ellis",
    "title": "JD Vance rakes in more cash after receiving Trump endorsement: report"
  },
  {
    "id": 4690,
    "mediaId": 2672,
    "date": "2022-04-23",
    "sentence": "",
    "author": "Jack Crosbie",
    "title": "J.D. Vance Promises Voters That He Really Means It — This Time"
  }
]