[
  {
    "id": 7762,
    "mediaId": 65,
    "date": "d2022-04-14T17:58",
    "sentence": "During a segment discussing the Senate candidacies of celebrity TV doctor Mehmet Oz and former star football player <span class='selected-term'>Herschel Walker</span>, Hostin decried the idea that Americans would vote to elect celebrities with no political experience, pointing to Trump as reason not to vote for them.",
    "author": "Brandon Gillespie",
    "title": "'The View's' Sunny Hostin claims Trump 'ran the country into the ground' despite multiple crises under Biden",
    "sentiment": "-0.409"
  }
]