[
  {
    "id": 5775,
    "mediaId": 136,
    "date": "2022-00-04",
    "sentence": "",
    "author": "Rob Minto",
    "title": "J.D. Vance's Book Sales Got Bigger Boost from Trump Than Netflix",
    "sentiment": "0.934"
  },
  {
    "id": 5873,
    "mediaId": 19,
    "date": "2022-00-04",
    "sentence": "",
    "author": "John Binder",
    "title": "J.D. Vance Takes Up the Populist Torch Despised by Republican Establishment",
    "sentiment": "-0.506"
  },
  {
    "id": 5535,
    "mediaId": 129,
    "date": "2022-00-15",
    "sentence": "",
    "author": "Marc Tracy",
    "title": "How Hollywood and the Media Fueled the Political Rise of J.D. Vance",
    "sentiment": "0"
  }
]