[
  {
    "id": 6405,
    "mediaId": 151,
    "date": "4/14/2022 12:00:00 AM",
    "sentence": "",
    "author": "",
    "title": "Ohio Republicans gang up to stop Vance endorsement"
  },
  {
    "id": 6378,
    "mediaId": 223,
    "date": "4/15/2022 12:00:00 AM",
    "sentence": "",
    "author": "Rebecca Downs",
    "title": "Donald Trump Endorses JD Vance for Closely Watched Senate Seat"
  },
  {
    "id": 6385,
    "mediaId": 223,
    "date": "4/15/2022 12:00:00 AM",
    "sentence": "",
    "author": "Rebecca Downs",
    "title": "Is the Media Jumping the Gun When it Comes to Warnings on Trump's Planned Endorsement in Ohio?"
  },
  {
    "id": 6300,
    "mediaId": 43,
    "date": "4/19/2022 12:00:00 AM",
    "sentence": "",
    "author": "",
    "title": "for Bluesday, April 19th"
  },
  {
    "id": 6232,
    "mediaId": 238,
    "date": "4/22/2022 12:00:00 AM",
    "sentence": "",
    "author": "",
    "title": "Opinion: Will Trumps base ever turn on him? Look to Ohio."
  },
  {
    "id": 6096,
    "mediaId": 195,
    "date": "4/28/2022 12:00:00 AM",
    "sentence": "",
    "author": "Caroline Vakil",
    "title": "Josh Hawley, Charlie Kirk to stump for Vance in Ohio"
  },
  {
    "id": 6044,
    "mediaId": 136,
    "date": "5/1/2022 12:00:00 AM",
    "sentence": "",
    "author": "Fatma Khaled",
    "title": "Greene 'Tired' of Candidates Like Mandel Who 'Learned to Speak MAGA'"
  },
  {
    "id": 5992,
    "mediaId": 195,
    "date": "5/2/2022 12:00:00 AM",
    "sentence": "",
    "author": "Julia Manchester",
    "title": "Vance waves off Trump fumbling his name: Im not worried about it at all"
  },
  {
    "id": 6009,
    "mediaId": 195,
    "date": "5/2/2022 12:00:00 AM",
    "sentence": "",
    "author": "Brad Dress",
    "title": "Trump fumbles JD Vances name at rally"
  },
  {
    "id": 5812,
    "mediaId": 195,
    "date": "5/4/2022 12:00:00 AM",
    "sentence": "",
    "author": "Julia Manchester",
    "title": "Five takeaways from the Ohio primaries"
  },
  {
    "id": 5828,
    "mediaId": 195,
    "date": "5/4/2022 12:00:00 AM",
    "sentence": "",
    "author": "Tal Axelrod",
    "title": "Vance wins Ohio Senate primary, handing Trump key victory"
  }
]