[
  {
    "id": 3624,
    "mediaId": 2590,
    "date": "2022-01-18",
    "sentence": "",
    "author": "Liz Skalka",
    "title": "Inside J.D. Vance's Possibly B.S. 'No B.S. Tour' Across Ohio"
  },
  {
    "id": 887,
    "mediaId": 2658,
    "date": "2022-02-14",
    "sentence": "",
    "author": "",
    "title": "Trump’s latest political obsession: The baseball team owner not toeing his line"
  },
  {
    "id": 1403,
    "mediaId": 2746,
    "date": "2022-02-15",
    "sentence": "",
    "author": "Seth McLaughlin",
    "title": "Kellyanne Conway endorses Jane Timken in Ohio Senate race, accepts role as senior adviser"
  },
  {
    "id": 1377,
    "mediaId": 2537,
    "date": "2022-02-16",
    "sentence": "",
    "author": "Jason Williams",
    "title": "U.S. Sen. Rob Portman endorses Jane Timken in crowded GOP primary for Ohio Senate seat"
  },
  {
    "id": 1665,
    "mediaId": 2658,
    "date": "2022-02-16",
    "sentence": "",
    "author": "",
    "title": "Portman backs Timken in crowded Ohio GOP primary"
  },
  {
    "id": 908,
    "mediaId": 2746,
    "date": "2022-02-16",
    "sentence": "",
    "author": "Seth McLaughlin",
    "title": "Jane Timken scores Sen. Rob Portman’s endorsement in Ohio GOP Senate race"
  },
  {
    "id": 45,
    "mediaId": 2641,
    "date": "2022-02-20",
    "sentence": "",
    "author": "Eric Mack",
    "title": "Jane Timken's Surge Begs Question on Trump Endorsement in Ohio"
  },
  {
    "id": 91,
    "mediaId": 2641,
    "date": "2022-02-22",
    "sentence": "",
    "author": "Brian Freeman",
    "title": "Sens. Ernst, Fischer, Capito Back Timken in Ohio GOP Senate Primary"
  },
  {
    "id": 13435,
    "mediaId": 8323,
    "date": "2022-03-16",
    "sentence": "",
    "author": "Associated Press",
    "title": "Ohio US Senate primary: Business in Russia scrutinized"
  },
  {
    "id": 9512,
    "mediaId": 6519,
    "date": "2022-03-19",
    "sentence": "",
    "author": "Peter Vicenzi",
    "title": "FreedomWorks Releases Ohio Senate Candidate Straw Poll Results"
  },
  {
    "id": 9392,
    "mediaId": 2540,
    "date": "2022-03-19",
    "sentence": "",
    "author": "Eva McKend and Andrea Cambron",
    "title": "'Back off, buddy': Two candidates get in each other's faces during Ohio GOP Senate debate"
  },
  {
    "id": 8908,
    "mediaId": 2573,
    "date": "2022-03-21",
    "sentence": "",
    "author": "Paul Steinhauser",
    "title": "After nearly trading blows in their first debate, Ohio GOP Senate candidates face off in round two"
  },
  {
    "id": 9276,
    "mediaId": 2625,
    "date": "2022-03-22",
    "sentence": "",
    "author": "Jacob Rosenberg",
    "title": "Here’s a Helpful Video Explaining Republicans’ 2022 Policy Agenda"
  },
  {
    "id": 9654,
    "mediaId": 2919,
    "date": "2022-03-22",
    "sentence": "",
    "author": "Nick Evans",
    "title": "In Ohio Republican Senate debate, candidates draw sharper distinctions"
  },
  {
    "id": 9726,
    "mediaId": 2702,
    "date": "2022-03-23",
    "sentence": "",
    "author": "Julia Manchester",
    "title": "Gibbons rolls out ad touting business experience as Ohio Senate primary turns ugly"
  },
  {
    "id": 9792,
    "mediaId": 2537,
    "date": "2022-03-28",
    "sentence": "",
    "author": "Haley BeMiller",
    "title": "False claims about 2020 election dominate debate between Ohio GOP U.S. Senate candidates"
  },
  {
    "id": 11736,
    "mediaId": 8480,
    "date": "2022-03-28",
    "sentence": "",
    "author": "Caroline Morse",
    "title": "Republican U.S. Senate candidates gearing up for Ohio primary"
  },
  {
    "id": 11709,
    "mediaId": 8358,
    "date": "2022-03-29",
    "sentence": "",
    "author": "",
    "title": "Republican Senate hopefuls say they expect ugly primary race"
  },
  {
    "id": 7227,
    "mediaId": 2526,
    "date": "2022-04-06",
    "sentence": "",
    "author": "John Binder",
    "title": "Poll: JD Vance Gains in Ohio Senate Race, Tied with Gibbons and Mandel for Lead"
  },
  {
    "id": 7141,
    "mediaId": 2572,
    "date": "2022-04-07",
    "sentence": "",
    "author": "Lisa Bennatan",
    "title": "As Ohio Senate hopefuls vie for Trump's support, one contender says he's the only one focused on the issues"
  },
  {
    "id": 6602,
    "mediaId": 8455,
    "date": "2022-04-15",
    "sentence": "",
    "author": "ASSOCIATED PRESS",
    "title": "GOP leaders in Ohio try to block Trump endorsement of Vance"
  },
  {
    "id": 5869,
    "mediaId": 2892,
    "date": "2022-04-15",
    "sentence": "",
    "author": "Richard Moorhead",
    "title": "Report: Trump Planning Game-Changing Endorsement in Red-Hot Ohio Republican Primary"
  },
  {
    "id": 5720,
    "mediaId": 2593,
    "date": "2022-04-15",
    "sentence": "",
    "author": "Richard Moorhead",
    "title": "Report: Trump Planning Game-Changing Endorsement in Red-Hot Ohio Republican Primary"
  },
  {
    "id": 5829,
    "mediaId": 6602,
    "date": "2022-04-18",
    "sentence": "",
    "author": "Shane Goldmacher",
    "title": "Mar-a-Lago machine: Trump as a modern-day party boss"
  },
  {
    "id": 5618,
    "mediaId": 2919,
    "date": "2022-04-19",
    "sentence": "",
    "author": "John Kosich",
    "title": "Dolan kicks off state tour ahead of GOP Senate primary"
  },
  {
    "id": 5905,
    "mediaId": 2731,
    "date": "2022-04-20",
    "sentence": "",
    "author": "John and Andy Schlafly",
    "title": "So Why Isn’t Biden Visiting Ukraine?"
  },
  {
    "id": 5692,
    "mediaId": 2746,
    "date": "2022-04-21",
    "sentence": "",
    "author": "Seth McLaughlin",
    "title": "J.D. Vance gets Trump bounce in Ohio Senate race: poll"
  },
  {
    "id": 4727,
    "mediaId": 8497,
    "date": "2022-04-21",
    "sentence": "",
    "author": "John London",
    "title": "Ohio US Senate candidates push to the finish ahead of primary"
  },
  {
    "id": 4859,
    "mediaId": 2514,
    "date": "2022-04-23",
    "sentence": "",
    "author": "Haley BeMiller",
    "title": "Donald Trump holds Ohio rally amid criticism of J.D. Vance endorsement for U.S. Senate"
  }
]